{"id":31591,"title":"Language of Flowers","authors":[{"name":"Greenaway, Kate","birth_year":1846,"death_year":1901}],"translators":[],"subjects":["Flower language","Flowers -- Poetry"],"bookshelves":[],"languages":["en"],"copyright":false,"media_type":"Text","formats":{"application/zip":"https://www.gutenberg.org/files/31591/31591.zip","text/plain; charset=us-ascii":"https://www.gutenberg.org/files/31591/31591.txt","text/html; charset=iso-8859-1":"https://www.gutenberg.org/files/31591/31591-h.zip","text/plain; charset=iso-8859-1":"https://www.gutenberg.org/files/31591/31591-8.zip","image/jpeg":"https://www.gutenberg.org/cache/epub/31591/pg31591.cover.medium.jpg","text/html":"https://www.gutenberg.org/ebooks/31591.html.images","text/plain":"https://www.gutenberg.org/ebooks/31591.txt.utf-8","application/epub+zip":"https://www.gutenberg.org/ebooks/31591.epub.images","application/rdf+xml":"https://www.gutenberg.org/ebooks/31591.rdf","application/x-mobipocket-ebook":"https://www.gutenberg.org/ebooks/31591.kindle.images"},"download_count":1543,"tagger-version":"v2.0.2"}