{"id":68157,"title":"Manual of the apiary","authors":[{"name":"Cook, Albert John","birth_year":1842,"death_year":1916}],"translators":[],"subjects":["Bee culture","Bees"],"bookshelves":[],"languages":["en"],"copyright":false,"media_type":"Text","formats":{"application/octet-stream":"https://www.gutenberg.org/files/68157/68157-h.zip","application/epub+zip":"https://www.gutenberg.org/ebooks/68157.epub.images","text/plain":"https://www.gutenberg.org/ebooks/68157.txt.utf-8","application/x-mobipocket-ebook":"https://www.gutenberg.org/ebooks/68157.kindle.images","application/rdf+xml":"https://www.gutenberg.org/ebooks/68157.rdf","application/zip":"https://www.gutenberg.org/files/68157/68157-0.zip","image/jpeg":"https://www.gutenberg.org/cache/epub/68157/pg68157.cover.small.jpg","text/plain; charset=us-ascii":"https://www.gutenberg.org/files/68157/68157-0.txt","text/html":"https://www.gutenberg.org/files/68157/68157-h/68157-h.htm"},"download_count":669}