{"id":1200,"title":"Gargantua and Pantagruel","authors":[{"name":"Rabelais, François","birth_year":null,"death_year":null}],"translators":[{"name":"Urquhart, Thomas, Sir","birth_year":1611,"death_year":1660},{"name":"Motteux, Peter Anthony","birth_year":1660,"death_year":1718}],"subjects":["Fantasy fiction, French -- Translations into English","Gargantua (Legendary character) -- Fiction","Giants -- Fiction"],"bookshelves":["Banned Books from Anne Haight's list","Best Books Ever Listings"],"languages":["en"],"copyright":false,"media_type":"Text","formats":{"text/plain; charset=utf-8":"https://www.gutenberg.org/files/1200/1200-0.zip","text/html; charset=iso-8859-1":"https://www.gutenberg.org/files/1200/1200-h/1200-h.htm","text/plain; charset=us-ascii":"https://www.gutenberg.org/files/1200/1200.zip","application/zip":"https://www.gutenberg.org/files/1200/1200-h.zip","image/jpeg":"https://www.gutenberg.org/cache/epub/1200/pg1200.cover.small.jpg","text/html":"https://www.gutenberg.org/ebooks/1200.html.images","application/x-mobipocket-ebook":"https://www.gutenberg.org/ebooks/1200.kindle.images","application/rdf+xml":"https://www.gutenberg.org/ebooks/1200.rdf","application/epub+zip":"https://www.gutenberg.org/ebooks/1200.epub.images"},"download_count":1686,"tagger-version":"v2.0.2"}