{"wordsCount":6574,"uniqueWordsCount":719,"ranks":{"highest":17797,"lowest":1},"levels":{"A1":{"count":282,"readability":84.84940675387892},"A2":{"count":108,"readability":91.48159415880743},"B1":{"count":87,"readability":96.79038637055066},"B2":{"count":47,"readability":98.75266200182537},"C1":{"count":24,"readability":99.48281107392759},"C2":{"count":10,"readability":99.86309704898083}},"words":[["i",293],["and",240],["to",206],["a",161],["the",157],["he",157],["was",146],["me",125],["my",110],["of",104],["you",100],["in",98],["said",84],["but",74],["him",72],["not",71],["with",58],["it",57],["is",54],["her",54],["she",52],["that",48],["want",44],["then",43],["queen",41],["there",40],["his",39],["man",38],["they",36],["very",36],["for",31],["am",29],["so",29],["did",29],["friends",29],["we",28],["at",28],["lord",28],["one",26],["going",26],["on",26],["son",25],["afraid",25],["too",25],["people",25],["were",25],["are",23],["because",23],["father",23],["like",23],["now",23],["king",22],["men",22],["husband",22],["had",21],["all",20],["kill",20],["think",20],["about",20],["this",19],["see",19],["came",19],["good",19],["when",19],["went",19],["please",19],["castle",18],["do",18],["be",18],["know",18],["god",18],["them",18],["out",18],["day",17],["no",17],["looked",17],["here",16],["can",16],["angry",16],["could",16],["rode",16],["back",15],["night",15],["or",14],["two",14],["some",14],["go",14],["lady",13],["room",13],["from",13],["come",13],["help",13],["why",13],["perhaps",13],["what",13],["killed",13],["army",13],["wrote",12],["little",12],["away",12],["prison",12],["tell",12],["die",12],["liked",12],["sorry",12],["put",12],["dead",11],["sometimes",11],["course",11],["write",11],["an",11],["lords",11],["church",11],["story",10],["our",10],["many",10],["say",10],["true",10],["stood",10],["old",10],["often",10],["lot",10],["work",10],["face",10],["five",10],["unhappy",10],["catholic",10],["woman",10],["after",10],["earl",10],["strong",10],["blood",10],["chapter",9],["give",9],["much",9],["nothing",9],["never",9],["asked",9],["down",9],["happy",9],["sang",9],["love",9],["big",9],["talk",9],["fight",9],["outside",9],["again",9],["quietly",8],["years",8],["tired",8],["letter",8],["life",8],["ill",8],["house",8],["protestant",8],["wanted",8],["talked",8],["letters",8],["friend",8],["well",8],["laughed",8],["ran",8],["town",8],["these",8],["behind",8],["took",8],["us",8],["three",7],["only",7],["twenty",7],["how",7],["mother",7],["english",7],["things",7],["time",7],["soon",7],["before",7],["marry",7],["young",7],["walked",7],["next",7],["everyone",7],["understand",7],["black",7],["wrong",7],["six",7],["up",7],["into",7],["boy",7],["poor",7],["gave",6],["slowly",6],["baby",6],["first",6],["stayed",6],["than",6],["slept",6],["enemies",6],["born",6],["find",6],["child",6],["wife",6],["arms",6],["dress",6],["over",6],["morning",6],["veil",6],["head",6],["executioner",6],["beautiful",5],["lies",5],["eyes",5],["important",5],["smiled",5],["country",5],["clothes",5],["difficult",5],["have",5],["better",5],["evening",5],["dark",5],["door",5],["got",5],["sleep",5],["kirk",5],["downstairs",5],["name",4],["began",4],["window",4],["horses",4],["road",4],["hands",4],["long",4],["free",4],["right",4],["has",4],["white",4],["lie",4],["loved",4],["angrily",4],["leave",4],["women",4],["rule",4],["tall",4],["thought",4],["wants",4],["found",4],["weeks",4],["sit",4],["try",4],["drank",4],["inside",4],["helped",4],["rooms",4],["other",4],["something",4],["red",4],["wicked",4],["minutes",4],["stupid",4],["floor",4],["cry",4],["waited",4],["wedding",4],["heard",4],["through",4],["week",3],["cold",3],["home",3],["dog",3],["watched",3],["queens",3],["married",3],["front",3],["forget",3],["remember",3],["minute",3],["knew",3],["pen",3],["yes",3],["would",3],["meet",3],["believe",3],["brother",3],["new",3],["more",3],["off",3],["near",3],["streets",3],["their",3],["pray",3],["thing",3],["without",3],["look",3],["need",3],["danced",3],["fell",3],["stairs",3],["friendly",3],["half",3],["stop",3],["those",3],["interested",3],["anything",3],["pregnant",3],["clever",3],["always",3],["worked",3],["hard",3],["small",3],["move",3],["knife",3],["hand",3],["bad",3],["held",3],["towards",3],["quiet",3],["smile",3],["quickly",3],["met",3],["who",3],["times",3],["under",3],["oh",3],["forgive",3],["prayed",3],["axe",3],["north",2],["goes",2],["children",2],["does",2],["ten",2],["last",2],["saw",2],["nearly",2],["thinks",2],["needs",2],["bring",2],["cannot",2],["lived",2],["year",2],["any",2],["girl",2],["eighteen",2],["sea",2],["pleased",2],["hope",2],["change",2],["shouted",2],["hate",2],["called",2],["famous",2],["churchman",2],["daughter",2],["let",2],["cried",2],["words",2],["books",2],["meeting",2],["between",2],["robert",2],["suddenly",2],["lover",2],["felt",2],["grandfather",2],["tried",2],["south",2],["stopped",2],["read",2],["teach",2],["ride",2],["needed",2],["sings",2],["listened",2],["death",2],["seven",2],["opened",2],["eat",2],["thank",2],["beside",2],["hot",2],["moved",2],["send",2],["another",2],["doing",2],["yesterday",2],["tonight",2],["june",2],["bed",2],["forgot",2],["horse",2],["bang",2],["ladies",2],["news",2],["garden",2],["doors",2],["wait",2],["flag",2],["picture",2],["keep",2],["listen",2],["eight",2],["block",2],["margin",2],["ago",1],["houses",1],["river",1],["trees",1],["along",1],["happened",1],["husbands",1],["months",1],["fore",1],["untrue",1],["hears",1],["happen",1],["dear",1],["everything",1],["french",1],["younger",1],["sixteen",1],["different",1],["still",1],["ship",1],["tells",1],["churches",1],["john",1],["hated",1],["don",1],["myself",1],["family",1],["sister",1],["countries",1],["writes",1],["nineteen",1],["green",1],["wore",1],["expensive",1],["great",1],["july",1],["marriage",1],["laughter",1],["hundreds",1],["days",1],["drink",1],["swim",1],["alive",1],["interesting",1],["evenings",1],["dances",1],["four",1],["march",1],["dinner",1],["table",1],["warm",1],["hungry",1],["chair",1],["round",1],["really",1],["second",1],["hold",1],["touch",1],["knives",1],["hit",1],["pulled",1],["hear",1],["drinking",1],["nice",1],["laugh",1],["matter",1],["crying",1],["run",1],["faster",1],["slow",1],["hours",1],["rain",1],["make",1],["summer",1],["ruled",1],["take",1],["older",1],["fighter",1],["far",1],["where",1],["stay",1],["upstairs",1],["visited",1],["arm",1],["singing",1],["remembered",1],["dirty",1],["sudden",1],["noise",1],["everybody",1],["hour",1],["wearing",1],["early",1],["walls",1],["windows",1],["way",1],["someone",1],["sold",1],["horrible",1],["pictures",1],["same",1],["spring",1],["miles",1],["excited",1],["divorce",1],["may",1],["hill",1],["armies",1],["theirs",1],["both",1],["killer",1],["kingdom",1],["today",1],["changes",1],["prisoner",1],["shut",1],["lost",1],["stronger",1],["mine",1],["forty",1],["told",1],["enemy",1],["lied",1],["get",1],["ask",1],["answer",1],["live",1],["nine",1],["writing",1],["afternoon",1],["tomorrow",1],["past",1],["dressed",1],["feet",1],["hundred",1],["open",1],["walk",1],["lifted",1],["once",1],["twice",1],["shoes",1],["everywhere",1],["bloody",1],["un",1],["happily",1],["end",1],["enjoyed",1],["reading",1],["net",1],["fascinating",1],["exciting",1],["cover",1],["page",1],["body",1],["text",1],["center",1]],"tagger-version":"v2.5.3"}