{"wordsCount":2730,"uniqueWordsCount":663,"ranks":{"highest":14392,"lowest":1},"levels":{"A1":{"count":279,"readability":83.11355311355312},"A2":{"count":91,"readability":88.82783882783883},"B1":{"count":84,"readability":93.62637362637363},"B2":{"count":68,"readability":97.72893772893774},"C1":{"count":39,"readability":99.34065934065934},"C2":{"count":13,"readability":100}},"words":[["i",107],["the",97],["and",86],["to",69],["a",66],["you",56],["that",56],["she",55],["was",53],["her",51],["my",34],["in",30],["of",29],["we",25],["there",25],["but",24],["not",23],["me",23],["he",23],["said",22],["this",22],["is",22],["cottage",22],["for",21],["it",21],["very",19],["with",18],["have",18],["wife",18],["about",16],["face",16],["when",15],["his",14],["then",14],["husband",14],["from",13],["one",12],["man",12],["if",12],["am",12],["are",12],["us",11],["at",11],["will",11],["went",10],["asked",10],["cried",10],["had",10],["house",10],["did",9],["our",9],["what",9],["tell",9],["yellow",9],["night",9],["be",9],["little",9],["see",8],["think",8],["so",8],["should",8],["child",8],["after",8],["girl",8],["go",7],["walked",7],["as",7],["room",7],["case",7],["now",7],["money",7],["sure",7],["ever",7],["told",7],["returned",6],["all",6],["going",6],["left",6],["pipe",6],["well",6],["do",6],["know",6],["took",6],["strange",6],["people",6],["some",6],["they",6],["come",6],["jack",6],["saw",6],["door",6],["again",6],["like",5],["day",5],["two",5],["on",5],["been",5],["help",5],["grant",5],["name",5],["away",5],["married",5],["suddenly",5],["why",5],["where",5],["who",5],["back",5],["woman",5],["everything",5],["him",4],["because",4],["must",4],["much",4],["more",4],["new",4],["off",4],["or",4],["years",4],["were",4],["until",4],["between",4],["met",4],["leave",4],["too",4],["near",4],["came",4],["never",4],["first",4],["time",4],["something",4],["effie",4],["home",4],["out",4],["here",4],["desk",4],["entered",3],["around",3],["finally",3],["needed",3],["has",3],["than",3],["just",3],["heard",3],["someone",3],["walking",3],["up",3],["into",3],["hat",3],["want",3],["inside",3],["please",3],["facts",3],["these",3],["three",3],["last",3],["appeared",3],["only",3],["seen",3],["death",3],["live",3],["can",3],["love",3],["good",3],["an",3],["front",3],["wanted",3],["ask",3],["hundred",3],["pounds",3],["gave",3],["happened",3],["past",3],["window",3],["call",3],["minutes",3],["stood",3],["truth",3],["enter",3],["trust",3],["could",3],["no",3],["photograph",3],["got",3],["mystery",3],["afraid",3],["long",3],["hand",3],["part",2],["walk",2],["park",2],["five",2],["baker",2],["street",2],["beg",2],["pardon",2],["waiting",2],["saying",2],["return",2],["likes",2],["particular",2],["explained",2],["look",2],["probably",2],["same",2],["stairs",2],["knocked",2],["need",2],["chair",2],["dear",2],["write",2],["many",2],["happy",2],["let",2],["young",2],["twenty",2],["lived",2],["both",2],["certificate",2],["decided",2],["mention",2],["large",2],["amount",2],["income",2],["six",2],["months",2],["other",2],["few",2],["weeks",2],["afterwards",2],["put",2],["ago",2],["by",2],["oh",2],["secret",2],["nothing",2],["thought",2],["looking",2],["watching",2],["upper",2],["frightened",2],["any",2],["living",2],["middle",2],["looked",2],["nervous",2],["laugh",2],["next",2],["early",2],["surprise",2],["anything",2],["mean",2],["before",2],["promise",2],["great",2],["marriage",2],["started",2],["creature",2],["found",2],["maid",2],["them",2],["find",2],["anyone",2],["replied",2],["fire",2],["received",2],["solve",2],["word",2],["would",2],["theory",2],["ran",2],["coming",2],["which",2],["wait",2],["god",2],["trusted",2],["turned",2],["moment",2],["ear",2],["pulled",2],["mask",2],["black",2],["laughed",2],["locket",2],["servant",2],["say",2],["aimless",1],["physical",1],["exercise",1],["spring",1],["persuaded",1],["hours",1],["almost",1],["sir",1],["page",1],["boy",1],["restless",1],["gentleman",1],["lost",1],["table",1],["big",1],["obvious",1],["costs",1],["seven",1],["twice",1],["silver",1],["bands",1],["cost",1],["itself",1],["mend",1],["instead",1],["buying",1],["talking",1],["without",1],["knocking",1],["upset",1],["down",1],["began",1],["visitor",1],["jumped",1],["preserve",1],["incognito",1],["smiling",1],["else",1],["turn",1],["person",1],["whom",1],["addressing",1],["friend",1],["secrets",1],["fortune",1],["barrier",1],["become",1],["stranger",1],["loves",1],["impatience",1],["widow",1],["old",1],["town",1],["called",1],["lawyer",1],["fever",1],["epidemic",1],["tragedy",1],["aunt",1],["also",1],["invested",1],["fell",1],["each",1],["hop",1],["merchant",1],["nice",1],["country",1],["inn",1],["houses",1],["single",1],["across",1],["field",1],["recent",1],["incident",1],["happily",1],["thing",1],["idea",1],["insisted",1],["certainly",1],["how",1],["surprised",1],["banker",1],["questions",1],["cheque",1],["forgot",1],["matter",1],["may",1],["age",1],["empty",1],["van",1],["furniture",1],["unnatural",1],["rigid",1],["closer",1],["disappeared",1],["tall",1],["answered",1],["neighbour",1],["shut",1],["rude",1],["completely",1],["asleep",1],["became",1],["aware",1],["dressed",1],["leaving",1],["waited",1],["moved",1],["quickly",1],["fright",1],["awake",1],["fresh",1],["air",1],["believe",1],["hiding",1],["city",1],["worried",1],["stopped",1],["minute",1],["imagine",1],["opened",1],["angry",1],["during",1],["telling",1],["discover",1],["cause",1],["sadness",1],["held",1],["tightly",1],["tried",1],["push",1],["sorry",1],["force",1],["way",1],["finished",1],["greatly",1],["relieved",1],["link",1],["discovered",1],["upstairs",1],["comfortable",1],["full",1],["length",1],["warned",1],["peace",1],["yesterday",1],["hearing",1],["story",1],["silent",1],["thinking",1],["distance",1],["papers",1],["destroyed",1],["yet",1],["duplicate",1],["knew",1],["talked",1],["visiting",1],["letters",1],["concluded",1],["those",1],["blackmail",1],["upon",1],["attractive",1],["worlds",1],["terrible",1],["disease",1],["horrible",1],["life",1],["feels",1],["safe",1],["unscrupulous",1],["attached",1],["discovers",1],["lives",1],["send",1],["tells",1],["knows",1],["while",1],["sleeping",1],["able",1],["convince",1],["alone",1],["returns",1],["promises",1],["wants",1],["get",1],["rid",1],["brings",1],["fortunately",1],["except",1],["correct",1],["tea",1],["message",1],["train",1],["station",1],["approached",1],["sake",1],["sternly",1],["friends",1],["rushed",1],["lighted",1],["corner",1],["wearing",1],["red",1],["dress",1],["white",1],["cry",1],["horror",1],["colour",1],["absolutely",1],["expression",1],["later",1],["behind",1],["coal",1],["staring",1],["holding",1],["throat",1],["does",1],["proud",1],["forced",1],["accept",1],["situation",1],["picture",1],["handsome",1],["intelligent",1],["obviously",1],["descent",1],["john",1],["noble",1],["cut",1],["myself",1],["race",1],["marry",1],["regretted",1],["unfortunately",1],["rather",1],["mine",1],["dark",1],["words",1],["mother",1],["continued",1],["healthy",1],["considered",1],["abandoning",1],["chance",1],["learned",1],["lose",1],["kept",1],["existence",1],["sent",1],["possible",1],["precaution",1],["gossip",1],["wore",1],["arrival",1],["beginning",1],["troubles",1],["tonight",1],["answer",1],["lifted",1],["kissed",1],["arms",1],["talk",1],["over",1],["comfortably",1],["better",1],["together",1],["another",1],["late",1],["bed",1],["becoming",1],["confident",1],["powers",1],["working",1],["hard",1],["enough",1],["whisper",1],["infinitely",1],["obliged",1],["end",1],["hope",1],["enjoyed",1],["reading",1],["english",1],["books",1],["net",1],["fascinating",1],["exciting",1]],"tagger-version":"v2.4.2"}