{"id":6762,"title":"Politics: A Treatise on Government","authors":[{"name":"Aristotle","birth_year":-384,"death_year":-322}],"translators":[{"name":"Ellis, William","birth_year":1730,"death_year":1801}],"subjects":["Political science -- Early works to 1800"],"bookshelves":["Classical Antiquity","Philosophy","Politics"],"languages":["en"],"copyright":false,"media_type":"Text","formats":{"application/zip":"https://www.gutenberg.org/files/6762/6762-h.zip","text/plain; charset=us-ascii":"https://www.gutenberg.org/files/6762/6762.zip","image/jpeg":"https://www.gutenberg.org/cache/epub/6762/pg6762.cover.medium.jpg","text/html; charset=us-ascii":"https://www.gutenberg.org/files/6762/6762-h/6762-h.htm","text/html":"https://www.gutenberg.org/ebooks/6762.html.images","application/x-mobipocket-ebook":"https://www.gutenberg.org/ebooks/6762.kindle.images","application/rdf+xml":"https://www.gutenberg.org/ebooks/6762.rdf","application/epub+zip":"https://www.gutenberg.org/ebooks/6762.epub.images","text/plain":"https://www.gutenberg.org/ebooks/6762.txt.utf-8"},"download_count":720}