{"wordsCount":69457,"uniqueWordsCount":6793,"ranks":{"highest":17958,"lowest":1},"levels":{"A1":{"count":492,"readability":75.8857998473876},"A2":{"count":467,"readability":82.1025958506702},"B1":{"count":837,"readability":88.24308565011447},"B2":{"count":1277,"readability":93.92573822652865},"C1":{"count":1400,"readability":98.46235800567258},"C2":{"count":695,"readability":99.96832572670861}},"words":[["the",4287],["of",2458],["to",2095],["and",1742],["a",1318],["her",1114],["in",1110],["that",932],["had",796],["was",793],["i",666],["she",657],["his",636],["it",616],["with",610],["as",609],["not",575],["for",559],["he",485],["isa",480],["on",455],["which",440],["but",440],["from",432],["'s",422],["be",417],["you",403],["by",361],["is",360],["at",348],["have",347],["lottie",298],["been",268],["so",244],["all",242],["or",236],["would",236],["him",230],["one",220],["this",211],["an",203],["when",200],["if",197],["were",196],["no",195],["my",194],["who",192],["gaspar",190],["god",188],["we",183],["me",182],["could",177],["what",170],["said",167],["up",164],["little",160],["will",154],["there",145],["they",143],["gideon",140],["like",140],["more",139],["brother",138],["has",128],["than",128],["are",127],["their",125],["your",124],["mr",123],["do",122],["might",120],["our",119],["such",118],["cora",117],["into",116],["may",115],["own",114],["lord",113],["now",112],["before",111],["very",110],["only",110],["upon",110],["never",110],["us",107],["over",104],["heart",104],["them",104],["must",103],["faith",101],["down",99],["how",98],["should",98],["out",96],["even",95],["gutenberg",93],["work",91],["young",91],["shall",91],["any",90],["project",88],["gritton",88],["some",88],["poor",88],["did",86],["time",85],["its",84],["father",84],["edith",83],["herself",83],["then",81],["wildwaste",81],["whom",80],["much",79],["away",78],["mrs",76],["girl",75],["can",73],["yet",73],["sister",72],["mind",72],["those",72],["man",71],["see",71],["madden",71],["miss",70],["where",69],["thought",69],["life",69],["go",69],["eardley",68],["let",68],["hand",68],["made",66],["after",66],["first",66],["ever",65],["every",65],["through",64],["well",63],["place",63],["himself",63],["come",62],["give",61],["make",61],["house",61],["without",61],["though",60],["felt",60],["words",60],["found",60],["most",59],["door",59],["night",57],["home",57],["soul",56],["last",56],["know",56],["way",56],["look",56],["once",55],["mother",55],["isa's",55],["long",54],["room",53],["good",53],["here",53],["money",53],["am",52],["under",51],["world",50],["about",50],["say",50],["men",50],["whose",49],["while",49],["back",49],["other",48],["left",48],["day",48],["light",47],["oh",47],["given",47],["looked",47],["face",47],["find",47],["almost",46],["still",46],["too",46],["love",46],["spirit",46],["eyes",45],["castle",45],["great",45],["seemed",45],["help",45],["stone",45],["many",44],["came",44],["master",44],["unto",44],["midianites",43],["within",43],["years",43],["nothing",43],["brought",43],["again",43],["bolder",43],["works",43],["lady",42],["heard",42],["people",42],["hope",42],["these",41],["holdich",41],["being",41],["think",41],["cause",41],["few",40],["knew",40],["replied",40],["axe",40],["morning",40],["word",40],["against",40],["arthur",40],["god's",39],["dear",39],["wife",39],["power",39],["evening",39],["indeed",39],["israel",39],["fear",38],["observed",38],["midian",37],["promise",37],["exclaimed",37],["why",37],["cried",37],["tell",37],["hands",37],["alone",37],["thou",37],["self",36],["full",36],["having",36],["care",36],["till",36],["side",36],["lay",35],["peace",35],["children",35],["thee",35],["rest",34],["speak",34],["around",34],["towards",34],["take",34],["christian",33],["two",33],["just",33],["earth",33],["also",33],["days",33],["anxious",33],["lottie's",33],["return",32],["lips",32],["mistress",32],["leave",32],["asked",32],["kind",32],["part",32],["e",31],["subject",31],["done",31],["lecture",31],["child",31],["cannot",31],["right",31],["thus",31],["passed",31],["lodge",31],["deborah",31],["things",30],["green",30],["cottage",30],["name",30],["hear",30],["set",30],["enemy",30],["woman",30],["another",30],["turned",29],["don't",29],["son",29],["least",29],["nature",29],["open",29],["put",29],["better",29],["strength",29],["feeling",29],["new",28],["old",28],["blessing",28],["visit",28],["scarcely",28],["often",28],["off",28],["bring",28],["always",28],["seen",28],["servant",28],["conscience",28],["hard",28],["hour",28],["small",28],["going",28],["nor",28],["vault",28],["feel",27],["death",27],["chapter",27],["took",27],["painful",27],["perhaps",27],["something",27],["less",27],["heaven",27],["forth",27],["hannah",27],["electronic",27],["triumph",26],["maid",26],["voice",26],["trouble",26],["pleasure",26],["strange",26],["however",26],["looking",26],["far",26],["together",26],["thoughts",26],["comfort",26],["sent",26],["ill",26],["sacrifice",26],["head",26],["o",25],["same",25],["joy",25],["duty",25],["suddenly",25],["received",25],["brethren",25],["means",25],["ye",25],["thy",25],["foundation",25],["known",24],["whether",24],["half",24],["carriage",24],["rather",24],["anything",24],["disappointment",24],["heavy",24],["entered",24],["rose",24],["keep",24],["can't",24],["silence",24],["ask",24],["message",23],["early",23],["yes",23],["husband",23],["wrong",23],["interest",23],["read",23],["rebekah",23],["terms",22],["service",22],["obedience",22],["believe",22],["called",22],["sound",22],["truth",22],["stay",22],["saw",22],["command",22],["appeared",22],["table",22],["prayer",22],["myself",22],["send",22],["use",21],["history",21],["bright",21],["clear",21],["black",21],["seems",21],["does",21],["went",21],["taken",21],["lost",21],["become",21],["behind",21],["hath",21],["steady",21],["illustrated",21],["lestrange",20],["each",20],["five",20],["returned",20],["during",20],["cousin",20],["able",20],["soon",20],["hardly",20],["added",20],["pray",20],["get",20],["stood",20],["told",20],["simple",20],["because",20],["christ",20],["call",20],["discontent",20],["i'm",20],["moment",20],["already",20],["copyright",20],["states",19],["country",19],["victory",19],["chosen",19],["strong",19],["trial",19],["happiness",19],["above",19],["sir",19],["three",19],["thing",19],["cold",19],["presence",19],["friend",19],["sin",19],["gaspar's",19],["struggle",19],["sure",19],["state",19],["trust",19],["dull",19],["following",19],["sight",19],["gold",19],["license",18],["sorrow",18],["evil",18],["friends",18],["true",18],["short",18],["meet",18],["beauty",18],["common",18],["tone",18],["honour",18],["effort",18],["both",18],["window",18],["difficulty",18],["charge",18],["land",18],["amongst",18],["laid",18],["meeting",18],["enough",18],["altar",18],["agreement",18],["others",17],["tree",17],["whole",17],["save",17],["school",17],["wish",17],["church",17],["spoke",17],["bear",17],["character",17],["led",17],["pain",17],["itself",17],["speaking",17],["gave",17],["pressed",17],["certain",17],["sentence",17],["account",17],["sat",17],["treasure",17],["pox",17],["united",16],["task",16],["grace",16],["uttered",16],["step",16],["kindness",16],["used",16],["especially",16],["present",16],["conversation",16],["deep",16],["enemies",16],["between",16],["either",16],["idea",16],["regard",16],["tears",16],["close",16],["miserable",16],["stand",16],["kept",16],["need",16],["search",16],["troubles",16],["pride",16],["study",16],["i'll",16],["below",16],["mine",15],["broken",15],["bed",15],["living",15],["spirits",15],["since",15],["hamlet",15],["clergyman",15],["doing",15],["eye",15],["pass",15],["baronet",15],["bitter",15],["endure",15],["tempted",15],["placed",15],["lionel",15],["affection",15],["trials",15],["human",15],["dying",15],["sympathy",15],["midst",15],["shop",15],["efforts",15],["darkness",15],["says",15],["it's",15],["family",15],["lad",15],["further",15],["property",15],["foe",15],["holy",15],["there's",15],["closed",15],["interview",15],["gilt",15],["edges",15],["donations",15],["london",14],["show",14],["health",14],["possession",14],["invalid",14],["dare",14],["uncle",14],["brother's",14],["except",14],["loved",14],["answer",14],["drive",14],["sunday",14],["course",14],["beautiful",14],["learned",14],["turn",14],["gentle",14],["expression",14],["question",14],["sick",14],["dark",14],["idol",14],["earthly",14],["destroy",14],["sudden",14],["beside",14],["low",14],["met",14],["sake",14],["sense",14],["draw",14],["saviour",14],["sickness",14],["heavenly",14],["distrust",14],["morrow",14],["loud",14],["seated",14],["i've",14],["length",14],["followed",14],["law",14],["water",14],["unable",14],["trademark",14],["ebook",13],["copy",13],["longer",13],["steward",13],["weary",13],["sunshine",13],["soft",13],["round",13],["surprise",13],["pastor",13],["instead",13],["walk",13],["slowly",13],["seat",13],["receive",13],["smile",13],["blessed",13],["deal",13],["proud",13],["repeated",13],["countenance",13],["raised",13],["times",13],["orissa",13],["blood",13],["ready",13],["possible",13],["cry",13],["hosts",13],["brief",13],["hundred",13],["seem",13],["beyond",13],["surely",13],["walked",13],["reply",13],["s",13],["knows",13],["courage",13],["caught",13],["sun",13],["position",13],["silent",13],["secret",13],["fruit",13],["letter",13],["engravings",13],["literary",13],["archive",13],["gideon's",12],["opening",12],["deemed",12],["daughter",12],["emotion",12],["sigh",12],["loss",12],["share",12],["papa",12],["sweet",12],["generous",12],["aware",12],["difficulties",12],["servants",12],["tried",12],["pursued",12],["else",12],["suffering",12],["past",12],["conduct",12],["knees",12],["appointed",12],["parent",12],["orphan",12],["fixed",12],["society",12],["parson",12],["danger",12],["themselves",12],["taking",12],["unhappy",12],["gone",12],["expected",12],["fingers",12],["saying",12],["fell",12],["opened",12],["throw",12],["ourselves",12],["arms",12],["free",12],["conflict",12],["joash",12],["success",12],["henry",12],["temptation",12],["camp",12],["price",12],["crown",12],["f",12],["scripture",11],["mercy",11],["air",11],["bound",11],["father's",11],["welcome",11],["delight",11],["case",11],["bitterness",11],["leaving",11],["dwelling",11],["rich",11],["praise",11],["continued",11],["order",11],["breakfast",11],["steps",11],["remain",11],["earnest",11],["manner",11],["tender",11],["sorry",11],["dwell",11],["relief",11],["hopes",11],["arose",11],["changed",11],["nay",11],["angel",11],["hearts",11],["greater",11],["england",11],["won",11],["opportunity",11],["cast",11],["cut",11],["forty",11],["giving",11],["dissension",11],["midianite",11],["due",11],["appear",11],["act",11],["road",11],["certainly",11],["neither",11],["she's",11],["maybe",11],["natural",11],["form",11],["thirty",11],["matter",11],["thinking",11],["shame",11],["glory",11],["cloth",11],["vicar",11],["information",11],["refund",11],["paragraph",11],["laws",10],["gathered",10],["influence",10],["companion",10],["tea",10],["spring",10],["painfully",10],["digby",10],["regarded",10],["real",10],["glad",10],["near",10],["built",10],["afraid",10],["promised",10],["understand",10],["religion",10],["written",10],["prospect",10],["none",10],["happy",10],["angry",10],["answered",10],["malice",10],["contained",10],["perfect",10],["believed",10],["really",10],["faithful",10],["startled",10],["resolved",10],["watch",10],["ear",10],["explanation",10],["mysterious",10],["making",10],["permitted",10],["pleasant",10],["dreary",10],["stopped",10],["dared",10],["trying",10],["weight",10],["obeyed",10],["divine",10],["leader",10],["drawn",10],["appears",10],["effect",10],["thousand",10],["candle",10],["usual",10],["rising",10],["honest",10],["book",10],["post",10],["permission",10],["high",10],["fire",10],["precious",10],["won't",10],["shook",10],["host",10],["baal",10],["remained",10],["fleece",10],["agree",10],["support",10],["infection",10],["access",10],["start",9],["c",9],["entering",9],["portion",9],["flight",9],["weak",9],["sister's",9],["spot",9],["therefore",9],["shadow",9],["perform",9],["line",9],["kindly",9],["steward's",9],["confidence",9],["quite",9],["master's",9],["end",9],["noble",9],["easily",9],["inquired",9],["baronet's",9],["cares",9],["maiden",9],["affectionate",9],["suggested",9],["fair",9],["vanity",9],["became",9],["experience",9],["frame",9],["business",9],["future",9],["doubt",9],["fact",9],["dry",9],["descended",9],["emotions",9],["abraham",9],["delivered",9],["four",9],["yoke",9],["beneath",9],["rock",9],["lowly",9],["rolled",9],["apartment",9],["try",9],["cheerful",9],["sacred",9],["gaze",9],["minutes",9],["hours",9],["paper",9],["captive",9],["hastily",9],["needed",9],["terrible",9],["patient",9],["sword",9],["distress",9],["abner",9],["hearing",9],["baker",9],["confession",9],["second",9],["personal",9],["news",9],["dew",9],["number",9],["active",9],["cora's",9],["lina",9],["including",9],["ground",8],["humble",8],["feeble",8],["filled",8],["faint",8],["path",8],["hair",8],["large",8],["object",8],["view",8],["city",8],["ago",8],["ought",8],["gives",8],["whatever",8],["everything",8],["interests",8],["enjoy",8],["liked",8],["until",8],["usually",8],["difficult",8],["bible",8],["troubled",8],["fears",8],["person",8],["brightness",8],["thrown",8],["cruel",8],["unworthy",8],["misery",8],["watching",8],["burden",8],["deeply",8],["memory",8],["arrived",8],["lodging",8],["shrank",8],["paid",8],["single",8],["floor",8],["peculiar",8],["freely",8],["engaged",8],["general",8],["point",8],["peevish",8],["constantly",8],["held",8],["covered",8],["thankful",8],["story",8],["glorious",8],["justice",8],["moses",8],["drew",8],["oppressed",8],["christians",8],["foes",8],["reach",8],["borne",8],["dangerous",8],["sign",8],["sank",8],["murmured",8],["scorn",8],["snuff",8],["girls",8],["yourself",8],["gently",8],["suffer",8],["bit",8],["bless",8],["connected",8],["late",8],["comes",8],["spread",8],["golden",8],["lying",8],["note",8],["muttered",8],["saved",8],["remember",8],["ladies",8],["break",8],["offer",8],["suspicion",8],["behold",8],["guest",8],["shine",8],["offering",8],["die",8],["consciousness",8],["beginning",8],["actually",8],["cart",8],["keen",8],["follow",8],["trumpet",8],["warriors",8],["aid",8],["fall",8],["hold",8],["curiosity",8],["anxiety",8],["d",8],["band",8],["illness",8],["sovereigns",8],["provide",8],["landlady",8],["calling",8],["questions",8],["stop",8],["trumpets",8],["illuminated",8],["fee",8],["l",7],["cost",7],["located",7],["sons",7],["field",7],["fight",7],["tidings",7],["sounded",7],["staircase",7],["lonely",7],["pretty",7],["treasures",7],["creature",7],["familiar",7],["smiling",7],["twenty",7],["possessed",7],["build",7],["joys",7],["doubtless",7],["looks",7],["brick",7],["manufactory",7],["street",7],["fancy",7],["wide",7],["greatly",7],["wanted",7],["spoken",7],["aloud",7],["worship",7],["quiet",7],["sadly",7],["change",7],["seven",7],["lord's",7],["feet",7],["bread",7],["gospel",7],["bent",7],["wicked",7],["charity",7],["rule",7],["nurse",7],["beloved",7],["narrow",7],["spiritual",7],["existence",7],["sum",7],["arm",7],["coming",7],["broke",7],["arrival",7],["pieces",7],["choose",7],["knowledge",7],["sought",7],["affections",7],["oppressive",7],["cheek",7],["threw",7],["delay",7],["journey",7],["wind",7],["wretched",7],["chill",7],["outward",7],["appearance",7],["simplicity",7],["wood",7],["lady's",7],["contact",7],["temper",7],["mean",7],["required",7],["homes",7],["removed",7],["offered",7],["eagerly",7],["suffered",7],["souls",7],["next",7],["bare",7],["fellow",7],["ungrateful",7],["arise",7],["he's",7],["perfectly",7],["happened",7],["join",7],["chair",7],["utterly",7],["special",7],["physical",7],["thinks",7],["returning",7],["rested",7],["battle",7],["softened",7],["began",7],["talk",7],["trembling",7],["pounds",7],["reproach",7],["saturday",7],["please",7],["innocent",7],["suspected",7],["shalt",7],["depart",7],["warm",7],["tychicus",7],["i'd",7],["reason",7],["righteous",7],["ventured",7],["honesty",7],["seek",7],["guilt",7],["pay",7],["notice",7],["force",7],["grove",7],["ten",7],["thine",7],["upstairs",7],["brow",7],["chamber",7],["mother's",7],["southampton",7],["trap",7],["ladder",7],["started",7],["ere",7],["prepare",7],["enemy's",7],["u",7],["distributing",7],["copies",7],["ebooks",7],["associated",7],["section",7],["using",6],["www",6],["egypt",6],["heroes",6],["instrument",6],["sermon",6],["casket",6],["refreshment",6],["bondage",6],["absence",6],["ascended",6],["echo",6],["along",6],["blue",6],["sky",6],["observation",6],["cousins",6],["laughed",6],["laugh",6],["realized",6],["windows",6],["remembrance",6],["gipsy",6],["sundays",6],["week",6],["lives",6],["surprised",6],["lie",6],["enjoyed",6],["talked",6],["one's",6],["patience",6],["prayers",6],["obey",6],["explain",6],["carefully",6],["forward",6],["valley",6],["sometimes",6],["recalled",6],["anguish",6],["satan",6],["hatred",6],["lurking",6],["desire",6],["higher",6],["result",6],["hoped",6],["fallen",6],["mystery",6],["fever",6],["midnight",6],["fairly",6],["damp",6],["wished",6],["spent",6],["satisfied",6],["sharp",6],["workmen",6],["inn",6],["sufficient",6],["emblem",6],["train",6],["east",6],["vain",6],["horse",6],["recognize",6],["carried",6],["hall",6],["hastened",6],["boudoir",6],["inclined",6],["sit",6],["pleasing",6],["knowing",6],["wages",6],["accepted",6],["carry",6],["meaning",6],["weeks",6],["edith's",6],["former",6],["clearly",6],["hide",6],["lead",6],["cross",6],["enjoyment",6],["lot",6],["attention",6],["chief",6],["different",6],["rejoice",6],["sinner",6],["makes",6],["prove",6],["fault",6],["brave",6],["live",6],["circumstances",6],["reflected",6],["wisdom",6],["art",6],["rough",6],["cup",6],["caused",6],["drink",6],["rustic",6],["waiting",6],["several",6],["marked",6],["eight",6],["box",6],["asking",6],["disappointed",6],["source",6],["class",6],["teach",6],["devotion",6],["taught",6],["girl's",6],["gentleman",6],["reflection",6],["formidable",6],["interrupted",6],["glimpse",6],["run",6],["instantly",6],["excitement",6],["quitted",6],["commanded",6],["quitting",6],["afternoon",6],["converse",6],["lifted",6],["breathed",6],["glance",6],["fast",6],["almighty",6],["prepared",6],["touched",6],["terror",6],["peril",6],["strengthen",6],["lightly",6],["you've",6],["honestly",6],["judge",6],["unless",6],["dust",6],["quick",6],["shown",6],["st",6],["fervent",6],["neighbourhood",6],["drinking",6],["expressed",6],["dead",6],["empty",6],["stairs",6],["grief",6],["bag",6],["resting",6],["sleep",6],["plead",6],["jordan",6],["public",6],["nervous",6],["feared",6],["wild",6],["entrance",6],["weariness",6],["reading",6],["bundle",6],["owner",6],["contain",6],["shillings",6],["moved",6],["wealth",6],["burst",6],["signs",6],["hast",6],["wrung",6],["blow",6],["blossoms",6],["perplexed",6],["drugget",6],["nervously",6],["discovered",6],["silver",6],["bags",6],["buried",6],["utter",6],["cobbler's",6],["cobbler",6],["possibly",6],["tale",6],["thief",6],["considerable",6],["torches",6],["pursuing",6],["distribute",6],["distribution",6],["comply",6],["tax",6],["anyone",5],["whatsoever",5],["online",5],["distributed",5],["conscious",5],["lessons",5],["claim",5],["weakness",5],["writing",5],["v",5],["suspicions",5],["confirmed",5],["denial",5],["exclamation",5],["brightly",5],["joyous",5],["fairy",5],["childhood",5],["pleasures",5],["heiress",5],["touch",5],["handle",5],["age",5],["newly",5],["flowers",5],["faces",5],["cloud",5],["charm",5],["manage",5],["purpose",5],["retreat",5],["wondering",5],["smoke",5],["visited",5],["bad",5],["mention",5],["nearly",5],["lectures",5],["haste",5],["confusion",5],["suspect",5],["daily",5],["wandered",5],["scene",5],["disciples",5],["labour",5],["thanks",5],["gossip",5],["lived",5],["strangers",5],["sensitive",5],["letting",5],["violent",5],["false",5],["indignation",5],["exactly",5],["breaking",5],["devoted",5],["stream",5],["disposed",5],["paradise",5],["disposition",5],["image",5],["admiration",5],["whisper",5],["disturbed",5],["providence",5],["various",5],["inexperienced",5],["invested",5],["feelings",5],["formed",5],["misfortune",5],["building",5],["fully",5],["fierce",5],["impossible",5],["best",5],["clung",5],["linked",5],["man's",5],["intended",5],["gritton's",5],["gratitude",5],["proof",5],["impatient",5],["companions",5],["finding",5],["station",5],["sensation",5],["driven",5],["porch",5],["dismissed",5],["tired",5],["stair",5],["immediately",5],["actual",5],["trees",5],["worse",5],["got",5],["irritable",5],["dreaded",5],["song",5],["forgotten",5],["shut",5],["granted",5],["sending",5],["judgment",5],["sufferings",5],["crosses",5],["examine",5],["gain",5],["overcome",5],["throughout",5],["cometh",5],["abide",5],["lesson",5],["address",5],["guard",5],["lies",5],["dinner",5],["iron",5],["mentioned",5],["restless",5],["smitten",5],["press",5],["pause",5],["merciful",5],["abode",5],["ah",5],["reflections",5],["poverty",5],["hymns",5],["youth",5],["weapons",5],["unusual",5],["wonder",5],["brown",5],["retired",5],["whenever",5],["listen",5],["worth",5],["reserve",5],["trusted",5],["quarter",5],["pulled",5],["standing",5],["likely",5],["collection",5],["grave",5],["deeds",5],["assigned",5],["gazed",5],["landscape",5],["sitting",5],["complaint",5],["current",5],["eager",5],["recurred",5],["pleased",5],["useless",5],["household",5],["occupation",5],["lighted",5],["mingled",5],["quietly",5],["refreshing",5],["experienced",5],["stranger",5],["forsaken",5],["promises",5],["rise",5],["risen",5],["departure",5],["fail",5],["silently",5],["strengthened",5],["getting",5],["solemnly",5],["ay",5],["em",5],["enter",5],["relieve",5],["baker's",5],["services",5],["holiday",5],["grant",5],["intention",5],["ran",5],["yielded",5],["crossed",5],["suspicious",5],["conviction",5],["worn",5],["selfish",5],["pure",5],["rejoicing",5],["pleaded",5],["thither",5],["tempter",5],["individual",5],["rain",5],["collins",5],["stone's",5],["doctor",5],["usefulness",5],["loves",5],["minute",5],["piece",5],["knelt",5],["'t",5],["want",5],["moving",5],["forces",5],["jerusalem",5],["king",5],["multitudes",5],["tents",5],["shock",5],["counsel",5],["plates",5],["displeased",5],["outside",5],["attracted",5],["unknown",5],["softly",5],["concealed",5],["canvas",5],["discovery",5],["hoards",5],["relieved",5],["regarding",5],["slow",5],["paused",5],["approached",5],["body",5],["heads",5],["appeal",5],["taylor",5],["madden's",5],["divided",5],["vessels",5],["princes",5],["mission",5],["protected",5],["org",5],["compliance",5],["medium",5],["replacement",5],["volunteers",5],["limited",5],["re",4],["check",4],["author",4],["produced",4],["bethlehem",4],["exiles",4],["richly",4],["domestic",4],["languor",4],["contents",4],["ii",4],["iii",4],["iv",4],["vi",4],["vii",4],["disclosure",4],["victorious",4],["crowned",4],["sorrows",4],["delicate",4],["park",4],["fragrance",4],["hearty",4],["cared",4],["limbs",4],["cheeks",4],["colour",4],["blossom",4],["hot",4],["addressed",4],["tall",4],["passing",4],["chose",4],["walking",4],["foot",4],["mile",4],["stands",4],["remind",4],["seldom",4],["compassion",4],["parish",4],["twice",4],["warmly",4],["digby's",4],["extravagance",4],["pious",4],["brings",4],["dealings",4],["repeat",4],["weather",4],["reached",4],["mounted",4],["compare",4],["missed",4],["realize",4],["talking",4],["mansion",4],["flush",4],["unpleasant",4],["willingly",4],["stern",4],["gloomy",4],["persons",4],["yours",4],["forehead",4],["contrary",4],["sad",4],["bliss",4],["brighter",4],["happier",4],["attending",4],["sweetness",4],["inward",4],["recognized",4],["committed",4],["resolution",4],["helping",4],["white",4],["increased",4],["women",4],["destroyed",4],["loving",4],["sternly",4],["vengeance",4],["injured",4],["shield",4],["bird",4],["bough",4],["cherished",4],["winds",4],["worldly",4],["months",4],["afterwards",4],["alarmed",4],["struggled",4],["forgive",4],["prison",4],["blessings",4],["year",4],["loneliness",4],["nearest",4],["departed",4],["sole",4],["catch",4],["accents",4],["bending",4],["breath",4],["occupied",4],["period",4],["season",4],["risk",4],["gladly",4],["availed",4],["grateful",4],["residence",4],["delightful",4],["unsightly",4],["six",4],["encouraged",4],["sufficiently",4],["safe",4],["affliction",4],["lofty",4],["expectation",4],["blowing",4],["protect",4],["deaf",4],["knock",4],["reception",4],["reserved",4],["domain",4],["ornament",4],["neglected",4],["furnished",4],["mortification",4],["showed",4],["roof",4],["accustomed",4],["utmost",4],["succeeded",4],["overflowing",4],["gracious",4],["punishment",4],["driving",4],["idolatry",4],["union",4],["powerful",4],["israelites",4],["fathers",4],["saith",4],["deliverance",4],["type",4],["directly",4],["sins",4],["perpetual",4],["leaves",4],["whence",4],["sooner",4],["preacher",4],["ages",4],["mercies",4],["deem",4],["apostle",4],["advantage",4],["receiving",4],["trace",4],["wrath",4],["opposition",4],["anger",4],["cases",4],["maketh",4],["spared",4],["unconscious",4],["closely",4],["wise",4],["rod",4],["deed",4],["threshing",4],["corn",4],["wine",4],["employ",4],["toil",4],["oak",4],["ophrah",4],["hitherto",4],["winter",4],["leaf",4],["latter",4],["parting",4],["wrapped",4],["aching",4],["breast",4],["walls",4],["probably",4],["reality",4],["handsome",4],["pinch",4],["sneer",4],["heat",4],["indulgence",4],["he'd",4],["reminded",4],["boy",4],["performing",4],["mournful",4],["helped",4],["sighed",4],["touching",4],["sovereign",4],["cloak",4],["conveyed",4],["convey",4],["volume",4],["impression",4],["links",4],["busy",4],["throwing",4],["encounter",4],["offence",4],["oppose",4],["falling",4],["watched",4],["blew",4],["scent",4],["papers",4],["you'd",4],["naturally",4],["foolish",4],["served",4],["convinced",4],["abruptly",4],["cargo",4],["embarrassed",4],["stake",4],["double",4],["value",4],["lip",4],["particular",4],["ship",4],["accounts",4],["prevent",4],["pleading",4],["pity",4],["casement",4],["mental",4],["distressed",4],["preparations",4],["we'll",4],["rooms",4],["lifeless",4],["intrude",4],["miracles",4],["moments",4],["gazing",4],["depths",4],["burning",4],["humility",4],["flesh",4],["apply",4],["assurance",4],["yea",4],["add",4],["raise",4],["thanksgiving",4],["additional",4],["giveth",4],["degree",4],["conquered",4],["shrink",4],["anxiously",4],["thank",4],["compromise",4],["performed",4],["suppose",4],["shutters",4],["miriam",4],["stir",4],["glancing",4],["turning",4],["penny",4],["example",4],["express",4],["preaching",4],["kingdom",4],["neighbours",4],["searching",4],["trusting",4],["slay",4],["disappeared",4],["hearted",4],["easy",4],["awkward",4],["consent",4],["altogether",4],["closing",4],["wishes",4],["printed",4],["wound",4],["denying",4],["unwilling",4],["win",4],["afflicted",4],["haunted",4],["string",4],["cover",4],["count",4],["absent",4],["involve",4],["wilt",4],["bullock",4],["tribe",4],["bold",4],["eventful",4],["revealed",4],["fury",4],["folly",4],["centre",4],["army",4],["marvellous",4],["reward",4],["compared",4],["escape",4],["resisted",4],["boys",4],["labours",4],["interrupting",4],["wants",4],["lines",4],["remembered",4],["pale",4],["noise",4],["heathen",4],["nursing",4],["locked",4],["ignorant",4],["firm",4],["glanced",4],["excited",4],["apparently",4],["here's",4],["hurriedly",4],["bonnet",4],["town",4],["working",4],["emphatically",4],["pursue",4],["expenses",4],["wont",4],["lest",4],["fearful",4],["direction",4],["deliver",4],["pursuit",4],["grieve",4],["sink",4],["weights",4],["gilded",4],["bottom",4],["inner",4],["covetousness",4],["unexpected",4],["slumber",4],["satisfaction",4],["keeping",4],["alarm",4],["solemn",4],["obtain",4],["clothes",4],["stout",4],["neighbour",4],["she'd",4],["linen",4],["folk",4],["dreadful",4],["frankly",4],["strike",4],["goes",4],["space",4],["perplexity",4],["shoulder",4],["chanced",4],["ascertain",4],["ain't",4],["kitchen",4],["seed",4],["sickening",4],["sleeping",4],["listening",4],["dream",4],["shelter",4],["paying",4],["questioned",4],["died",4],["disfigurement",4],["forced",4],["benefactor",4],["apostles",4],["immediate",4],["ephraim",4],["fruits",4],["record",4],["acted",4],["page",4],["widow",4],["motive",4],["pages",4],["equipment",4],["succoth",4],["penuel",4],["zebah",4],["zalmunna",4],["sixpence",4],["editions",4],["creating",4],["copying",4],["phrase",4],["displaying",4],["format",4],["status",4],["posted",4],["holder",4],["fees",4],["providing",4],["requirements",4],["website",4],["provided",4],["donate",4],["damages",4],["included",3],["date",3],["attack",3],["shepherd",3],["babylon",3],["rescued",3],["t",3],["nelson",3],["edinburgh",3],["york",3],["trodden",3],["bestowed",3],["bubbles",3],["xx",3],["joyful",3],["lingering",3],["nursery",3],["stored",3],["picture",3],["amusement",3],["delights",3],["garden",3],["wondered",3],["approach",3],["visiting",3],["quivering",3],["youthful",3],["sauntered",3],["avenue",3],["graceful",3],["expressive",3],["gladness",3],["distance",3],["dropped",3],["staring",3],["soap",3],["conspicuous",3],["brightening",3],["eyed",3],["scarlet",3],["assured",3],["bull",3],["attend",3],["gravely",3],["accompany",3],["holiness",3],["merely",3],["openly",3],["holdich's",3],["happiest",3],["fine",3],["miles",3],["lovely",3],["views",3],["directions",3],["straight",3],["florence",3],["serious",3],["nice",3],["merry",3],["calm",3],["text",3],["needful",3],["reader",3],["previous",3],["crippled",3],["victim",3],["splendid",3],["fondly",3],["flow",3],["playful",3],["doubts",3],["congenial",3],["peaceful",3],["removal",3],["perception",3],["corruption",3],["lingered",3],["fond",3],["spend",3],["hero",3],["desired",3],["bubble",3],["dislike",3],["previously",3],["nest",3],["wayside",3],["constrained",3],["safer",3],["scattered",3],["marriage",3],["deepened",3],["murmur",3],["truly",3],["jacob",3],["job",3],["deeper",3],["leading",3],["parent's",3],["fatherless",3],["orphan's",3],["older",3],["jamaica",3],["relative",3],["minister",3],["weighed",3],["articulate",3],["sentences",3],["silenced",3],["dealt",3],["dread",3],["yearned",3],["possess",3],["settled",3],["residing",3],["venture",3],["recovered",3],["excuse",3],["uncle's",3],["heath",3],["desert",3],["taste",3],["crushed",3],["procure",3],["benefactress",3],["joined",3],["agreeable",3],["conveyance",3],["north",3],["driver",3],["features",3],["whip",3],["aspect",3],["absolute",3],["chilled",3],["cutting",3],["boxes",3],["observe",3],["apartments",3],["suppressed",3],["complain",3],["chairs",3],["serve",3],["furniture",3],["misgivings",3],["occasions",3],["described",3],["odd",3],["habits",3],["grow",3],["creatures",3],["unkind",3],["earliest",3],["ways",3],["grown",3],["irritation",3],["tempered",3],["fatherly",3],["april",3],["impressions",3],["saint",3],["practical",3],["web",3],["sisera",3],["receives",3],["scriptures",3],["ancient",3],["traced",3],["mountains",3],["stain",3],["canaan",3],["hordes",3],["warlike",3],["triumphed",3],["reproof",3],["dominion",3],["preserved",3],["vale",3],["stooped",3],["ambition",3],["sand",3],["later",3],["sweep",3],["flood",3],["midianites'",3],["grasp",3],["slave",3],["addition",3],["content",3],["praised",3],["third",3],["dwellings",3],["unfrequently",3],["preserve",3],["follows",3],["clouded",3],["redeemer",3],["forget",3],["unbelieving",3],["submission",3],["necessity",3],["concealment",3],["employed",3],["consideration",3],["branches",3],["fit",3],["bye",3],["dearest",3],["saints",3],["annoyed",3],["merited",3],["nearer",3],["sinful",3],["smooth",3],["exchanged",3],["across",3],["holiest",3],["revenge",3],["intense",3],["stillness",3],["tenement",3],["running",3],["shy",3],["john",3],["soothe",3],["particularly",3],["cheerfully",3],["circle",3],["hunting",3],["awaiting",3],["discouraged",3],["lively",3],["anecdote",3],["couldn't",3],["husband's",3],["a'most",3],["'most",3],["reverence",3],["infirmities",3],["helpless",3],["procured",3],["we've",3],["kindest",3],["arter",3],["dreamily",3],["hearer",3],["distinctly",3],["play",3],["nobody",3],["awoke",3],["preceding",3],["recollection",3],["tenderly",3],["delighted",3],["restrain",3],["rebuke",3],["duties",3],["somewhat",3],["front",3],["wore",3],["mused",3],["screen",3],["gray",3],["objects",3],["morn",3],["dried",3],["favour",3],["peevishly",3],["putting",3],["market",3],["shipping",3],["revolving",3],["determined",3],["remarked",3],["nigh",3],["vessel",3],["timidly",3],["twas",3],["goods",3],["west",3],["shaking",3],["keenly",3],["collect",3],["finish",3],["rapid",3],["slightly",3],["afford",3],["possibility",3],["succeeding",3],["suited",3],["prisoner",3],["freedom",3],["ungraciously",3],["you'll",3],["moisture",3],["graciously",3],["amidst",3],["occupations",3],["party",3],["attended",3],["monday",3],["bearing",3],["stronger",3],["confirmation",3],["beaming",3],["seeing",3],["created",3],["eternal",3],["messenger",3],["mighty",3],["despised",3],["race",3],["memories",3],["hiding",3],["instruments",3],["manasseh",3],["israel's",3],["smite",3],["hesitated",3],["spake",3],["feast",3],["bade",3],["pour",3],["presented",3],["alas",3],["nations",3],["lo",3],["righteousness",3],["acceptable",3],["preparing",3],["learn",3],["perfection",3],["supply",3],["contemplated",3],["banner",3],["fainting",3],["ended",3],["intellectual",3],["explained",3],["brighten",3],["wonderful",3],["wrinkled",3],["bowed",3],["shawl",3],["telling",3],["stirred",3],["pledge",3],["didn't",3],["decision",3],["deny",3],["pharisee",3],["setting",3],["shake",3],["burned",3],["bog",3],["sisters",3],["refuge",3],["advice",3],["disfigured",3],["killed",3],["knocked",3],["fatal",3],["yesterday",3],["separated",3],["brightened",3],["spare",3],["alive",3],["fresh",3],["occurred",3],["evidently",3],["scraps",3],["courtesy",3],["maddens",3],["questioning",3],["witness",3],["grew",3],["resentment",3],["banish",3],["aversion",3],["induce",3],["trembled",3],["steadily",3],["losing",3],["humbled",3],["guests",3],["investment",3],["yield",3],["audible",3],["misgiving",3],["friday",3],["bursting",3],["top",3],["ordered",3],["exposed",3],["comrades",3],["narrative",3],["direct",3],["idolatrous",3],["beheld",3],["mouth",3],["shrine",3],["speech",3],["recorded",3],["naphtali",3],["tabor",3],["lake",3],["idle",3],["historical",3],["plain",3],["river",3],["strain",3],["perish",3],["grasped",3],["wait",3],["generation",3],["riches",3],["lawful",3],["neglect",3],["office",3],["inspired",3],["mount",3],["whosoever",3],["doeth",3],["beat",3],["exchanging",3],["induced",3],["niece",3],["fain",3],["connection",3],["inclination",3],["pressing",3],["ragged",3],["strangely",3],["b",3],["shed",3],["verses",3],["voices",3],["schoolmistress",3],["stamp",3],["lose",3],["baby",3],["asleep",3],["welcomed",3],["purse",3],["contented",3],["seeking",3],["replaced",3],["commercial",3],["wearily",3],["thin",3],["slip",3],["supplication",3],["remains",3],["mark",3],["handwriting",3],["sob",3],["soiled",3],["article",3],["middle",3],["hurried",3],["outer",3],["debt",3],["suggestion",3],["fiercely",3],["chance",3],["obliged",3],["channel",3],["satisfy",3],["thankfulness",3],["encouragement",3],["rejected",3],["jews",3],["falls",3],["paul",3],["surrounded",3],["war",3],["carrying",3],["faltered",3],["gathering",3],["striking",3],["highest",3],["salvation",3],["beware",3],["handful",3],["meal",3],["fading",3],["generations",3],["sea",3],["shout",3],["bringing",3],["weigher",3],["smallest",3],["move",3],["firmly",3],["stories",3],["faintly",3],["plate",3],["breathe",3],["fill",3],["guidance",3],["gotten",3],["spell",3],["corpse",3],["flash",3],["bid",3],["grasping",3],["dearly",3],["swelled",3],["threshold",3],["red",3],["greet",3],["wet",3],["echoed",3],["green's",3],["indignant",3],["passion",3],["stones",3],["worritting",3],["swelling",3],["eardley's",3],["dishonesty",3],["gradually",3],["breathing",3],["mad",3],["informed",3],["village",3],["ungenerous",3],["rendered",3],["suggest",3],["remote",3],["forgiven",3],["humiliation",3],["remove",3],["addressing",3],["affair",3],["indifference",3],["grumbling",3],["pulling",3],["starting",3],["entirely",3],["overpowering",3],["notwithstanding",3],["pang",3],["tedious",3],["supports",3],["worshipped",3],["instance",3],["prisoners",3],["medicine",3],["stretched",3],["oppressor",3],["benighted",3],["arduous",3],["visible",3],["safely",3],["profit",3],["weakened",3],["disgrace",3],["separation",3],["humiliating",3],["reputation",3],["mist",3],["twilight",3],["feverish",3],["headache",3],["repugnance",3],["malady",3],["consider",3],["clasped",3],["guide",3],["erring",3],["listened",3],["reaching",3],["vicar's",3],["catching",3],["coachman",3],["regards",3],["followers",3],["ephraimites",3],["powers",3],["kings",3],["downstairs",3],["request",3],["gentleness",3],["whither",3],["drops",3],["reparation",3],["bell",3],["discover",3],["horror",3],["woman's",3],["assistance",3],["owns",3],["concerning",3],["throne",3],["french",3],["illustrations",3],["readable",3],["edition",3],["rev",3],["royalties",3],["complying",3],["derivative",3],["entity",3],["paragraphs",3],["official",3],["user",3],["royalty",3],["applicable",3],["payments",3],["defect",3],["defective",3],["disclaimer",3],["liability",3],["warranties",3],["limitation",3],["foundation's",3],["anywhere",2],["parts",2],["restrictions",2],["english",2],["types",2],["valiant",2],["armies",2],["aliens",2],["gift",2],["commend",2],["fireside",2],["viii",2],["ix",2],["x",2],["xi",2],["xii",2],["xiii",2],["xiv",2],["xv",2],["tongues",2],["xvi",2],["xvii",2],["xviii",2],["xix",2],["xxi",2],["xxii",2],["xxiii",2],["xxiv",2],["xxv",2],["xxvi",2],["conclusion",2],["revisited",2],["years'",2],["impatience",2],["broad",2],["whispered",2],["books",2],["sources",2],["recollections",2],["auld",2],["lang",2],["syne",2],["childish",2],["eleven",2],["robe",2],["mossy",2],["notes",2],["music",2],["ancestors",2],["dragged",2],["bounded",2],["dawn",2],["apple",2],["plant",2],["exotic",2],["skilfully",2],["tended",2],["petals",2],["healthful",2],["discipline",2],["mirth",2],["barely",2],["site",2],["longed",2],["shrubbery",2],["picturesque",2],["flat",2],["improved",2],["shape",2],["belong",2],["flock",2],["suit",2],["hesitation",2],["affairs",2],["pecuniary",2],["managed",2],["christianity",2],["schoolmaster",2],["series",2],["begin",2],["grassy",2],["mound",2],["rural",2],["italy",2],["native",2],["tongue",2],["ministry",2],["stayed",2],["wit",2],["comprehend",2],["harsh",2],["indulgent",2],["hate",2],["besides",2],["reminds",2],["arrows",2],["doubtful",2],["consistent",2],["kiss",2],["oppression",2],["bordered",2],["lark",2],["sing",2],["ease",2],["mirror",2],["dress",2],["accusation",2],["affected",2],["bridle",2],["clasping",2],["flower",2],["life's",2],["bereavement",2],["summit",2],["sterling",2],["shortly",2],["instinctive",2],["marvel",2],["resentful",2],["gloom",2],["altered",2],["hedge",2],["lionel's",2],["mortified",2],["soaring",2],["pit",2],["ruling",2],["goodness",2],["communion",2],["wounded",2],["disguise",2],["associations",2],["approaching",2],["strained",2],["devote",2],["preferred",2],["intuitively",2],["selecting",2],["relatives",2],["barren",2],["evident",2],["ordinary",2],["attractions",2],["favourable",2],["persuaded",2],["dash",2],["eccentricity",2],["redeemed",2],["buoyant",2],["store",2],["alms",2],["colours",2],["height",2],["march",2],["brilliant",2],["damped",2],["chilling",2],["effects",2],["lame",2],["skirted",2],["fancied",2],["pointing",2],["redeem",2],["disheartened",2],["groups",2],["elderly",2],["parlour",2],["calculated",2],["conversing",2],["explore",2],["uncarpeted",2],["elegancies",2],["economy",2],["penuriousness",2],["legs",2],["bookcase",2],["curtain",2],["closer",2],["chafe",2],["annoy",2],["unpruned",2],["corrected",2],["singular",2],["shoots",2],["infirmity",2],["greatest",2],["characteristic",2],["contempt",2],["luxury",2],["refinement",2],["persuading",2],["allow",2],["assistant",2],["arrangement",2],["passionate",2],["derived",2],["visits",2],["nightingale's",2],["nightingale",2],["arranged",2],["contrast",2],["refined",2],["elegance",2],["discomfort",2],["poorer",2],["lift",2],["addresses",2],["separate",2],["vide",2],["fig",2],["yards",2],["repose",2],["israelite",2],["inhabitants",2],["strongholds",2],["descendants",2],["guided",2],["successful",2],["prophet",2],["balaam",2],["lapse",2],["nation",2],["numerous",2],["attempt",2],["completely",2],["joshua",2],["fought",2],["deliverer",2],["egyptians",2],["gods",2],["christ's",2],["central",2],["egyptian",2],["devouring",2],["wept",2],["indirectly",2],["desolation",2],["leaders",2],["trample",2],["inflict",2],["severe",2],["term",2],["burdens",2],["intruder",2],["habitual",2],["fix",2],["houses",2],["mournfully",2],["vanities",2],["invasion",2],["decay",2],["harass",2],["eternity",2],["rebellious",2],["practically",2],["secretly",2],["repine",2],["frequently",2],["therewith",2],["alway",2],["deprived",2],["considered",2],["renounced",2],["rob",2],["heritage",2],["goodly",2],["contention",2],["bar",2],["defending",2],["footsteps",2],["gall",2],["eden",2],["hearers",2],["saddened",2],["injunction",2],["needlessly",2],["ashes",2],["oil",2],["mourning",2],["heaviness",2],["passeth",2],["understanding",2],["wheat",2],["flail",2],["viewed",2],["evidence",2],["sap",2],["crush",2],["grain",2],["render",2],["protection",2],["luxurious",2],["fewer",2],["enduring",2],["struggling",2],["amounting",2],["rebellion",2],["unnumbered",2],["comfortable",2],["lighter",2],["thanking",2],["intrusion",2],["simile",2],["motion",2],["traversed",2],["harboured",2],["timid",2],["greeted",2],["shabby",2],["sallow",2],["habitually",2],["indulged",2],["gadding",2],["relations",2],["absolutely",2],["ungracious",2],["expose",2],["acquaintance",2],["acquaintances",2],["unlike",2],["valetudinarian",2],["difference",2],["angrily",2],["related",2],["soften",2],["displeasure",2],["attentive",2],["al'ays",2],["al",2],["'ays",2],["woe",2],["elder",2],["dulness",2],["protector",2],["s'pose",2],["'pose",2],["perceived",2],["bees",2],["meat",2],["that's",2],["teaching",2],["elegantly",2],["toilette",2],["comment",2],["acknowledged",2],["vague",2],["fulfil",2],["hasty",2],["hardness",2],["kindliness",2],["approbation",2],["sex",2],["furze",2],["marred",2],["cottages",2],["repair",2],["neat",2],["ample",2],["redeeming",2],["feature",2],["thence",2],["woods",2],["towers",2],["climate",2],["stale",2],["joining",2],["inconvenience",2],["idiot",2],["introduce",2],["sticking",2],["betrayed",2],["nervousness",2],["chiefly",2],["foundered",2],["uninsured",2],["lucky",2],["indian",2],["matters",2],["milk",2],["jug",2],["attached",2],["importance",2],["tightly",2],["enabled",2],["seconds",2],["utterance",2],["ears",2],["wandering",2],["demand",2],["increase",2],["blame",2],["captain",2],["bewildered",2],["satisfactory",2],["noticed",2],["instant",2],["shaken",2],["strict",2],["remarks",2],["constant",2],["fret",2],["worry",2],["greeting",2],["charged",2],["surrender",2],["invitation",2],["irksome",2],["hideous",2],["withheld",2],["stately",2],["swiftly",2],["distant",2],["gratification",2],["crowded",2],["ford",2],["divinity",2],["persecuted",2],["creation",2],["glass",2],["peter",2],["flowed",2],["encourage",2],["shrunk",2],["accomplish",2],["wherewith",2],["commission",2],["hence",2],["unleavened",2],["cakes",2],["awaited",2],["designed",2],["staff",2],["vanished",2],["mortal",2],["obeying",2],["sinking",2],["uphold",2],["sorrowful",2],["offers",2],["stained",2],["wholly",2],["flame",2],["kindled",2],["becomes",2],["sojourn",2],["waited",2],["brim",2],["response",2],["visitor",2],["enable",2],["fearlessly",2],["presumptuous",2],["conquerors",2],["foliage",2],["budding",2],["shuts",2],["readily",2],["anticipated",2],["sweetest",2],["exchange",2],["lonesome",2],["chide",2],["afeard",2],["solitary",2],["heroic",2],["trod",2],["wife's",2],["fender",2],["wasn't",2],["thriving",2],["larger",2],["relapsed",2],["listener",2],["drunken",2],["mammon",2],["earned",2],["clean",2],["religious",2],["sheep",2],["ploughman",2],["hardest",2],["key",2],["doubted",2],["ideas",2],["publican",2],["guilty",2],["swept",2],["converted",2],["blind",2],["bolder's",2],["opinionative",2],["condemnation",2],["crisis",2],["virtues",2],["ark",2],["shore",2],["shows",2],["hollowness",2],["soul's",2],["safety",2],["repentance",2],["enables",2],["david",2],["visitation",2],["escort",2],["disliked",2],["remedy",2],["rheumatism",2],["blows",2],["fits",2],["younger",2],["deborah's",2],["fled",2],["tenderness",2],["habit",2],["hardship",2],["arrange",2],["inquiry",2],["rushed",2],["clapped",2],["indulge",2],["betraying",2],["unnecessary",2],["clumsy",2],["salt",2],["retiring",2],["inflicted",2],["scattering",2],["pushed",2],["undecided",2],["amuse",2],["aroused",2],["bosom",2],["intimate",2],["lawyer",2],["healed",2],["eagerness",2],["serves",2],["wronged",2],["fraud",2],["stammered",2],["declaration",2],["absorbed",2],["resembles",2],["retrace",2],["repulsive",2],["snare",2],["distressing",2],["delicacy",2],["subdued",2],["injustice",2],["insect",2],["silken",2],["ball",2],["tomb",2],["winged",2],["overheard",2],["match",2],["unlucky",2],["metaphorically",2],["incidental",2],["giant",2],["circles",2],["slight",2],["deception",2],["commandments",2],["incense",2],["burnt",2],["execution",2],["marvelled",2],["perilous",2],["rush",2],["enterprise",2],["slew",2],["explosion",2],["entertained",2],["witnessed",2],["demanded",2],["insult",2],["son's",2],["depth",2],["sacrificed",2],["abiezer",2],["gather",2],["roused",2],["superstition",2],["fetters",2],["messengers",2],["asher",2],["zebulon",2],["boyhood",2],["jezreel",2],["galilee",2],["places",2],["lately",2],["persuade",2],["awful",2],["tremble",2],["refused",2],["enclosed",2],["families",2],["commands",2],["bears",2],["snares",2],["atonement",2],["priestly",2],["deigns",2],["royal",2],["rejoiced",2],["meditation",2],["repeating",2],["heareth",2],["sayings",2],["floods",2],["write",2],["unusually",2],["suppressing",2],["needs",2],["relation",2],["announced",2],["playfully",2],["strongly",2],["opposed",2],["intelligence",2],["mistaken",2],["seriously",2],["devotional",2],["dazzled",2],["desirable",2],["neighbouring",2],["pack",2],["hunted",2],["encouraging",2],["horrible",2],["imagine",2],["hears",2],["returns",2],["favourite",2],["steal",2],["patiently",2],["peacefully",2],["concluded",2],["hum",2],["babe",2],["attempted",2],["sufferer",2],["proceed",2],["undertake",2],["dropping",2],["tuition",2],["likewise",2],["worked",2],["sabbath",2],["ridicule",2],["frown",2],["statistics",2],["feeding",2],["saviour's",2],["equally",2],["fulfilled",2],["offerings",2],["paved",2],["sprang",2],["cleared",2],["tidy",2],["month",2],["occurrence",2],["deserted",2],["needle",2],["pointed",2],["missive",2],["showing",2],["rude",2],["signature",2],["tore",2],["envelope",2],["escaped",2],["overpowered",2],["blotted",2],["bin",2],["cant",2],["git",2],["sold",2],["brain",2],["calculation",2],["fountain",2],["june",2],["plenty",2],["mustn't",2],["summons",2],["quaint",2],["jesting",2],["dusty",2],["maid's",2],["recoiled",2],["bush",2],["mood",2],["washed",2],["scrubbed",2],["problem",2],["laying",2],["consumptive",2],["hospital",2],["bournemouth",2],["doctors",2],["applying",2],["picking",2],["rolling",2],["minds",2],["minded",2],["remarkable",2],["increasing",2],["miraculous",2],["vouchsafed",2],["wool",2],["prayed",2],["thirsty",2],["proclaim",2],["proclamation",2],["melt",2],["bringeth",2],["shared",2],["selection",2],["lapped",2],["brook",2],["complete",2],["foremost",2],["humbler",2],["action",2],["fishermen",2],["sanctified",2],["zeal",2],["defeat",2],["melting",2],["wherefore",2],["germ",2],["renew",2],["wither",2],["rooted",2],["harvest",2],["birth",2],["manly",2],["storm",2],["harder",2],["jesus",2],["struck",2],["knell",2],["crushing",2],["boiling",2],["removing",2],["tray",2],["hither",2],["boards",2],["dim",2],["machine",2],["hunt",2],["sensible",2],["replace",2],["stars",2],["glimmering",2],["wall",2],["desk",2],["easier",2],["pick",2],["extreme",2],["planks",2],["pressure",2],["ranged",2],["curious",2],["yellow",2],["impulse",2],["proportion",2],["size",2],["dilated",2],["eve",2],["sore",2],["tempt",2],["parents",2],["pastor's",2],["violently",2],["dimly",2],["sounds",2],["miser",2],["dressed",2],["lock",2],["lawless",2],["vaults",2],["annoyance",2],["spreading",2],["dismissal",2],["rosy",2],["secrecy",2],["precaution",2],["possessions",2],["unfastening",2],["bolts",2],["advancing",2],["proceeded",2],["expect",2],["welfare",2],["frank",2],["intolerable",2],["chain",2],["carpet",2],["flushed",2],["ironing",2],["unexpectedly",2],["neighbour's",2],["heartily",2],["heated",2],["rubbing",2],["praying",2],["descending",2],["warn't",2],["warn",2],["measured",2],["drawl",2],["unwelcome",2],["earnestly",2],["tap",2],["displease",2],["exaggerated",2],["preserving",2],["sobbing",2],["obstinate",2],["sobbed",2],["credit",2],["promising",2],["entreating",2],["merciless",2],["entreaties",2],["drove",2],["raw",2],["untutored",2],["hang",2],["straw",2],["mere",2],["vice",2],["slightest",2],["truant",2],["neck",2],["forgot",2],["willing",2],["harm",2],["arisen",2],["unjust",2],["recourse",2],["expedition",2],["assent",2],["complicated",2],["heavily",2],["fifteen",2],["drip",2],["produce",2],["witted",2],["maintained",2],["pallet",2],["desolate",2],["elbow",2],["prize",2],["slept",2],["wherever",2],["resolutely",2],["garments",2],["props",2],["curse",2],["slaughter",2],["conclude",2],["providential",2],["multitude",2],["tent",2],["fiery",2],["containing",2],["foundations",2],["loosed",2],["standard",2],["consolation",2],["commencing",2],["final",2],["dwelt",2],["besetting",2],["pacing",2],["formal",2],["christopher",2],["fifty",2],["hotel",2],["furrowed",2],["briefly",2],["largely",2],["profits",2],["exercise",2],["crime",2],["barriers",2],["stores",2],["yielding",2],["hardened",2],["exposure",2],["ours",2],["selfishness",2],["restraint",2],["forgiveness",2],["strait",2],["social",2],["honoured",2],["knee",2],["principal",2],["guess",2],["sunset",2],["beguile",2],["retire",2],["convenient",2],["hadn't",2],["infected",2],["afore",2],["somewhere",2],["obligation",2],["intuitive",2],["hazard",2],["permanent",2],["quarantine",2],["adjoining",2],["worketh",2],["descend",2],["blighted",2],["abroad",2],["pillow",2],["quietness",2],["excite",2],["sympathizing",2],["gay",2],["glided",2],["welled",2],["admired",2],["comparative",2],["risked",2],["braved",2],["cruelly",2],["energy",2],["brimming",2],["rapidly",2],["forbidden",2],["honey",2],["suckle",2],["mantled",2],["ring",2],["aged",2],["resign",2],["summer",2],["convalescent",2],["innocence",2],["he'll",2],["depend",2],["glances",2],["hell",2],["finally",2],["armed",2],["pitcher",2],["lamp",2],["crash",2],["glare",2],["numbers",2],["frantic",2],["countrymen",2],["discomfited",2],["flying",2],["fords",2],["oreb",2],["zeeb",2],["display",2],["idols",2],["discomfit",2],["mostly",2],["uncertain",2],["blast",2],["displayed",2],["according",2],["shattered",2],["brilliance",2],["sounding",2],["precepts",2],["earthen",2],["christian's",2],["takes",2],["sarcasm",2],["insisted",2],["frightful",2],["insensible",2],["injuries",2],["gunpowder",2],["agent",2],["shouting",2],["crowd",2],["opportunities",2],["hungry",2],["worldliness",2],["unselfishness",2],["flashed",2],["drooping",2],["fly",2],["uttering",2],["warning",2],["alike",2],["generosity",2],["plunder",2],["uneasy",2],["shiver",2],["cave",2],["coin",2],["trance",2],["awake",2],["horrors",2],["situation",2],["quickly",2],["widow's",2],["bustled",2],["impart",2],["somehow",2],["frightened",2],["breathless",2],["unburdened",2],["kettle",2],["admit",2],["murdered",2],["astonishment",2],["inexpressible",2],["hannah's",2],["condition",2],["rewarded",2],["resembled",2],["tortured",2],["base",2],["restore",2],["lacked",2],["disbelief",2],["piety",2],["restored",2],["isolation",2],["marking",2],["feels",2],["victories",2],["errors",2],["widening",2],["important",2],["parliament",2],["slain",2],["comparison",2],["refresh",2],["secure",2],["avenger",2],["murderer",2],["clouds",2],["pilgrim",2],["chaplet",2],["wings",2],["stings",2],["coloured",2],["frontispiece",2],["vignette",2],["library",2],["travel",2],["spain",2],["m",2],["poitou",2],["original",2],["steel",2],["h",2],["w",2],["concept",2],["registered",2],["research",2],["redistribution",2],["promoting",2],["available",2],["redistributing",2],["obtaining",2],["based",2],["references",2],["prominently",2],["copied",2],["vanilla",2],["ascii",2],["specified",2],["receipt",2],["accordance",2],["computer",2],["damage",2],["warranty",2],["costs",2],["legal",2],["breach",2],["lieu",2],["electronically",2],["implied",2],["widest",2],["computers",2],["exempt",2],["federal",2],["contributions",2],["email",2],["solicit",2],["title",1],["release",1],["language",1],["tim",1],["lindell",1],["proofreading",1],["team",1],["https",1],["pgdp",1],["net",1],["paternoster",1],["row",1],["preface",1],["attempting",1],["illustrate",1],["examined",1],["studded",1],["originality",1],["endeavouring",1],["waxed",1],["lowliest",1],["depressing",1],["imperfectly",1],["executed",1],["humbly",1],["despiseth",1],["humblest",1],["effectual",1],["sparkled",1],["fawn's",1],["fawn",1],["oaken",1],["flit",1],["longest",1],["childhood's",1],["playroom",1],["toys",1],["doll",1],["miniature",1],["china",1],["traveller",1],["donning",1],["sheltered",1],["dells",1],["violets",1],["footed",1],["deer",1],["canary",1],["tamer",1],["fragile",1],["oppressing",1],["springing",1],["elastic",1],["turf",1],["colourless",1],["snowdrop",1],["buds",1],["reared",1],["expanding",1],["flecked",1],["spending",1],["suitable",1],["matured",1],["intimately",1],["auburn",1],["gazelle",1],["mirroring",1],["feats",1],["charming",1],["tastes",1],["differ",1],["architect",1],["admires",1],["ideal",1],["geni",1],["transplanted",1],["bodily",1],["smaller",1],["streets",1],["newness",1],["yellowish",1],["undarkened",1],["soot",1],["edge",1],["morass",1],["blindless",1],["sprinkled",1],["gorse",1],["tells",1],["reverenced",1],["recommend",1],["proteg",1],["blushes",1],["training",1],["affirmative",1],["eighty",1],["criticize",1],["preachers",1],["meetings",1],["confessing",1],["professes",1],["continent",1],["abused",1],["ostentatious",1],["plunged",1],["ostensible",1],["estate",1],["convince",1],["infidels",1],["treasured",1],["sauntering",1],["cock",1],["marble",1],["extensive",1],["invited",1],["spire",1],["yonder",1],["preached",1],["jesus'",1],["clergymen",1],["feed",1],["hallowed",1],["spoilt",1],["witty",1],["confidential",1],["ancestral",1],["mixed",1],["jest",1],["shamefully",1],["trustful",1],["hazel",1],["abrupt",1],["laughing",1],["mimicking",1],["silly",1],["rudeness",1],["tries",1],["unkindness",1],["description",1],["psalms",1],["shoot",1],["'",1],["darts",1],["alight",1],["pierce",1],["application",1],["venturing",1],["reprove",1],["darling",1],["imprint",1],["remembrances",1],["otherwise",1],["resemblance",1],["unmurmuring",1],["vigorous",1],["pleasantly",1],["dimpling",1],["soar",1],["instilled",1],["partook",1],["imagination",1],["simply",1],["dangers",1],["dimmed",1],["accuse",1],["surveying",1],["girlish",1],["serenity",1],["regular",1],["allowance",1],["adornment",1],["devoting",1],["equal",1],["combated",1],["wearing",1],["jewelled",1],["bracelet",1],["bud",1],["expands",1],["teachers",1],["blooming",1],["halo",1],["blest",1],["quality",1],["blown",1],["glittered",1],["prismatic",1],["tints",1],["rainbow",1],["alienated",1],["poisoned",1],["shaft",1],["quiver",1],["hidden",1],["gaiety",1],["awhile",1],["vindictive",1],["intruding",1],["blighting",1],["malicious",1],["confiding",1],["genius",1],["passions",1],["pained",1],["jacob's",1],["paternal",1],["shielded",1],["joseph's",1],["joseph",1],["accuser",1],["exaltation",1],["assaults",1],["exalted",1],["blessedness",1],["hereafter",1],["infernal",1],["aught",1],["wrongs",1],["stroke",1],["motherless",1],["thenceforth",1],["imparted",1],["dissolution",1],["delirium",1],["glazing",1],["watcher",1],["disburden",1],["parched",1],["inaudible",1],["imprinted",1],["solemnity",1],["ponder",1],["opinion",1],["tie",1],["courteous",1],["delaying",1],["reside",1],["exciting",1],["offending",1],["performance",1],["lordly",1],["considerate",1],["purchase",1],["expanse",1],["surrounding",1],["changes",1],["oasis",1],["buying",1],["superintend",1],["operations",1],["mix",1],["cottagers",1],["evenings",1],["county",1],["eccentric",1],["commonplace",1],["completion",1],["sprung",1],["patrimony",1],["slender",1],["dispensing",1],["glittering",1],["hired",1],["overclouded",1],["be's",1],["storied",1],["staringly",1],["sheltering",1],["blinds",1],["vulgarity",1],["untidy",1],["barefooted",1],["unwonted",1],["apparition",1],["numbed",1],["uncourteous",1],["dispel",1],["complaints",1],["leisure",1],["interior",1],["unattractive",1],["essential",1],["amounted",1],["matched",1],["haphazard",1],["broker's",1],["broker",1],["painted",1],["shelf",1],["entire",1],["anticipate",1],["disregard",1],["casual",1],["annoying",1],["transact",1],["angles",1],["graphic",1],["writer",1],["humorously",1],["rudiments",1],["ridiculous",1],["unamiable",1],["pruning",1],["traits",1],["acquired",1],["prune",1],["estimation",1],["rigidity",1],["branch",1],["resident",1],["hourly",1],["handed",1],["conveniences",1],["esteeming",1],["luxuries",1],["sympathize",1],["money's",1],["grovelling",1],["subordinate",1],["avarice",1],["gaining",1],["insight",1],["forcible",1],["compelled",1],["positive",1],["cheering",1],["speedy",1],["unite",1],["carking",1],["courses",1],["narratives",1],["weave",1],["chapters",1],["autumn",1],["holidays",1],["celebrated",1],["tranquillity",1],["forgetting",1],["rugged",1],["crags",1],["shutting",1],["memory's",1],["vines",1],["olive",1],["pastures",1],["waters",1],["causeless",1],["swarm",1],["locusts",1],["destroying",1],["wasting",1],["dens",1],["caves",1],["sinners",1],["chastise",1],["keturah",1],["perished",1],["punished",1],["defend",1],["battles",1],["drave",1],["amorites",1],["redemption",1],["achieved",1],["privileges",1],["purchased",1],["backslidings",1],["resembling",1],["afflictions",1],["bereavements",1],["graves",1],["miseries",1],["owe",1],["chiefs",1],["names",1],["visitations",1],["griefs",1],["cuts",1],["crop",1],["famine",1],["disobedience",1],["tide",1],["weep",1],["rolls",1],["unwisely",1],["builds",1],["ties",1],["earthy",1],["spoiler",1],["wrest",1],["robs",1],["bountiful",1],["envious",1],["gates",1],["inheritor",1],["showered",1],["affirm",1],["impracticable",1],["invades",1],["abodes",1],["turneth",1],["habitations",1],["misunderstood",1],["peaceably",1],["qualified",1],["harmony",1],["principle",1],["majority",1],["uncharitableness",1],["pours",1],["springs",1],["casts",1],["venomed",1],["wilderness",1],["herbs",1],["stalled",1],["ox",1],["purge",1],["burnings",1],["achings",1],["fourth",1],["assertion",1],["yourselves",1],["brows",1],["regrets",1],["weigh",1],["err",1],["exclaim",1],["lays",1],["scourge",1],["mistrust",1],["couldst",1],["careth",1],["garment",1],["rapacious",1],["custom",1],["oxen",1],["wield",1],["defer",1],["spray",1],["clothe",1],["chaff",1],["garner",1],["portico",1],["cushions",1],["privation",1],["discontented",1],["wear",1],["harbouring",1],["clay",1],["element",1],["immortality",1],["shrinking",1],["examination",1],["serene",1],["tribulation",1],["dungeon",1],["competence",1],["undeserved",1],["murmuring",1],["depressed",1],["inhabited",1],["petulance",1],["harshness",1],["cruelty",1],["persecution",1],["theirs",1],["squalid",1],["coldness",1],["jolting",1],["gravel",1],["grounds",1],["carts",1],["ruts",1],["boggy",1],["soil",1],["intensely",1],["arises",1],["unholy",1],["longing",1],["retribution",1],["longings",1],["meditations",1],["authoritative",1],["pervaded",1],["awe",1],["footman",1],["livery",1],["unfurnished",1],["farm",1],["prime",1],["complexion",1],["stoop",1],["consequent",1],["protracted",1],["contracted",1],["unpleasing",1],["dissatisfaction",1],["peevishness",1],["fellows",1],["startle",1],["thundering",1],["raps",1],["loudness",1],["disproportioned",1],["occasion",1],["humouredly",1],["announce",1],["modest",1],["aggrieved",1],["unfortunately",1],["disagreeable",1],["irritated",1],["retort",1],["liking",1],["antiquated",1],["whimsical",1],["robinson",1],["crusoe",1],["applied",1],["languidly",1],["grandees",1],["chilly",1],["offices",1],["ignorance",1],["naive",1],["frankness",1],["manners",1],["detected",1],["snuffing",1],["thermometer",1],["regulated",1],["declare",1],["defiance",1],["etiquette",1],["dish",1],["oblivious",1],["viands",1],["growing",1],["smilingly",1],["mistakes",1],["excused",1],["truthful",1],["polish",1],["intercourse",1],["brushed",1],["silky",1],["tresses",1],["pains",1],["philosophy",1],["rheumatics",1],["totaller",1],["brutal",1],["addicted",1],["intemperance",1],["hovel",1],["den",1],["absconded",1],["deserting",1],["employment",1],["incapacitated",1],["who's",1],["clinging",1],["diverged",1],["jolly",1],["gardener'",1],["naively",1],["tremulousness",1],["barring",1],["emphatic",1],["philanthropist",1],["switched",1],["riding",1],["hint",1],["poetry",1],["thoughtfully",1],["verse",1],["supremely",1],["denies",1],["e'en",1],["'en",1],["uneasiness",1],["saddest",1],["upholding",1],["quieted",1],["frivolous",1],["other's",1],["hinder",1],["cowardly",1],["offend",1],["cowardice",1],["wrestled",1],["darkening",1],["natures",1],["peculiarly",1],["nurtured",1],["cradle",1],["beneficence",1],["sorrowing",1],["womanly",1],["sterner",1],["appreciated",1],["throbbed",1],["uneasily",1],["bronze",1],["urn",1],["hissing",1],["meagre",1],["repast",1],["tract",1],["dotted",1],["patches",1],["blossoming",1],["picturesqueness",1],["foreground",1],["hovels",1],["squalor",1],["moss",1],["lichen",1],["clustering",1],["ivy",1],["ruins",1],["originally",1],["pretension",1],["erected",1],["clusters",1],["browed",1],["memorial",1],["penurious",1],["huge",1],["square",1],["windowed",1],["pile",1],["mortar",1],["breezes",1],["polluted",1],["leafy",1],["turrets",1],["ruder",1],["cuckoo's",1],["cuckoo",1],["overlooking",1],["verdant",1],["treacherous",1],["contrasting",1],["disadvantage",1],["withered",1],["loaf",1],["misses",1],["robbing",1],["servant's",1],["caddy",1],["report",1],["cue",1],["screwed",1],["commencement",1],["passengers",1],["stammer",1],["stretching",1],["poured",1],["letters",1],["nerved",1],["scrutinising",1],["emptying",1],["pot",1],["rapidity",1],["breathlessness",1],["lashes",1],["fragmentary",1],["orphan'",1],["unendurable",1],["tremulous",1],["deceived",1],["thousands",1],["invest",1],["consulted",1],["indies",1],["staked",1],["crew",1],["waves",1],["blamed",1],["ejaculated",1],["ghastly",1],["suffused",1],["sunk",1],["strengthening",1],["persuasion",1],["remainder",1],["nerves",1],["tune",1],["refer",1],["undrinkable",1],["draughts",1],["recommended",1],["grievance",1],["pettish",1],["bills",1],["ordering",1],["inveighed",1],["reckless",1],["complained",1],["disinclined",1],["settle",1],["solitude",1],["resistance",1],["seconded",1],["petition",1],["wretchedly",1],["tumble",1],["spoil",1],["fairest",1],["accorded",1],["bitterly",1],["nevertheless",1],["summoned",1],["exquisitely",1],["varied",1],["saunter",1],["conducted",1],["formality",1],["themes",1],["tenants",1],["delicacies",1],["invalids",1],["employments",1],["afforded",1],["unmixed",1],["bestowing",1],["uncomfortable",1],["tuesday",1],["bide",1],["clothed",1],["plains",1],["mamre",1],["jabbok",1],["sinai",1],["valour",1],["salutation",1],["befallen",1],["vent",1],["sorely",1],["pharaoh",1],["avenge",1],["shortened",1],["unmindful",1],["groans",1],["thrice",1],["beholdeth",1],["omniscient",1],["ocean",1],["beholding",1],["directed",1],["sunbeams",1],["concentrated",1],["focus",1],["kindle",1],["pillar",1],["melted",1],["penitential",1],["contrition",1],["unfitness",1],["lowlier",1],["authority",1],["wrought",1],["miracle",1],["talkest",1],["tarry",1],["entertain",1],["kid",1],["temple",1],["consecrated",1],["food",1],["broth",1],["consumed",1],["astonished",1],["mortal's",1],["deigned",1],["guise",1],["jehovah",1],["shallum",1],["seasons",1],["glean",1],["preach",1],["centuries",1],["dismayed",1],["extends",1],["bestow",1],["acceptance",1],["contrite",1],["indwelling",1],["transient",1],["thereby",1],["granting",1],["adoring",1],["crucifixion",1],["crowneth",1],["conquers",1],["blight",1],["mar",1],["hills",1],["leafless",1],["beams",1],["boughs",1],["gird",1],["motto",1],["cordial",1],["worried",1],["parties",1],["purest",1],["gratifies",1],["cheerless",1],["appreciate",1],["doubly",1],["grocer's",1],["grocer",1],["dolefully",1],["speaks",1],["creeping",1],["impulsive",1],["insufficient",1],["rid",1],["melancholy",1],["warrior",1],["cheered",1],["parted",1],["latch",1],["wreck",1],["featured",1],["hung",1],["streaked",1],["beard",1],["sunken",1],["chest",1],["rheumatic",1],["parson's",1],["isn't",1],["helplessness",1],["quarrel",1],["disorderly",1],["quarrelsome",1],["drop",1],["poison",1],["wetted",1],["bating",1],["overcharges",1],["mistake",1],["doctrine",1],["sends",1],["admiring",1],["calls",1],["prosperity",1],["birds",1],["prey",1],["interrupt",1],["understood",1],["counting",1],["crying",1],["abhor",1],["repent",1],["infallible",1],["pope",1],["opinions",1],["disputed",1],["alter",1],["dissent",1],["punishing",1],["exult",1],["publican's",1],["ruined",1],["wretch",1],["smothered",1],["nought",1],["mansions",1],["confident",1],["resigned",1],["sweeping",1],["twin",1],["forms",1],["temptations",1],["raft",1],["temperance",1],["respectability",1],["stem",1],["failures",1],["imperfections",1],["rottenness",1],["merits",1],["presumption",1],["fold",1],["pardoning",1],["goliath",1],["grievous",1],["crossing",1],["doctress",1],["labourer",1],["education",1],["nobly",1],["ruffian",1],["brains",1],["poker",1],["labouring",1],["carvings",1],["highwayman",1],["prays",1],["sober",1],["savage",1],["frets",1],["earn",1],["mentioning",1],["deferential",1],["ned",1],["welcoming",1],["accompanying",1],["destitute",1],["girdled",1],["sparkle",1],["saucer",1],["amused",1],["couple",1],["transition",1],["warmed",1],["radiant",1],["shady",1],["fireless",1],["grate",1],["shivering",1],["chilliness",1],["sickly",1],["cheerfulness",1],["expostulatingly",1],["candid",1],["professions",1],["truthfully",1],["coldly",1],["necessary",1],["deference",1],["nicely",1],["vex",1],["eavesdropping",1],["eats",1],["retreated",1],["uncourteously",1],["periodical",1],["perusal",1],["copious",1],["powder",1],["sheet",1],["mentally",1],["loan",1],["interesting",1],["anecdotes",1],["recluse",1],["regret",1],["disheartening",1],["newspaper",1],["referred",1],["stuttering",1],["mistook",1],["speaker",1],["neutralize",1],["impress",1],["contradiction",1],["adding",1],["falsehood",1],["rustling",1],["prolong",1],["chastisement",1],["cooled",1],["gratified",1],["warp",1],["revelations",1],["rectitude",1],["endeavour",1],["perceiving",1],["indifferent",1],["enjoyments",1],["becoming",1],["retraced",1],["damping",1],["rebekah's",1],["unimpressionable",1],["granite",1],["pitied",1],["prosperous",1],["furnace",1],["plaintively",1],["lamented",1],["caterpillar",1],["spinning",1],["cocoon",1],["sets",1],["diligently",1],["weaving",1],["forcing",1],["barrier",1],["hospitable",1],["board",1],["attract",1],["elasticity",1],["gratify",1],["tuned",1],["harp",1],["harmonious",1],["jarred",1],["discordant",1],["married",1],["fortune",1],["bride",1],["suns",1],["orbit",1],["speedily",1],["glow",1],["fates",1],["sports",1],["characters",1],["concerns",1],["soul'",1],["mars",1],["spirituality",1],["legion",1],["incessantly",1],["theme",1],["development",1],["parable",1],["orchards",1],["essence",1],["rises",1],["fraught",1],["pertained",1],["sanctuary",1],["idolater",1],["trusty",1],["represented",1],["heedlessly",1],["excuses",1],["interpose",1],["delays",1],["unquestioning",1],["apprehended",1],["felled",1],["decisive",1],["scabbard",1],["morning's",1],["informer",1],["spy",1],["probable",1],["uncompromising",1],["fidelity",1],["furious",1],["enraged",1],["worshippers",1],["defender",1],["descendant",1],["debasing",1],["worshipping",1],["bowing",1],["faced",1],["whilst",1],["jerubbaal",1],["mockery",1],["joash's",1],["rally",1],["patriotism",1],["bonds",1],["oppressors",1],["slopes",1],["hermon",1],["shores",1],["gennesareth",1],["banks",1],["northern",1],["liberators",1],["amalekites",1],["pitched",1],["adjacent",1],["esdraelon",1],["megiddo",1],["south",1],["samaria",1],["kishon",1],["sisera's",1],["triumphant",1],["recur",1],["brace",1],["tribes",1],["barak",1],["jeoparded",1],["prophetess",1],["goeth",1],["manassite",1],["bitterest",1],["exalt",1],["addeth",1],["noah",1],["mocking",1],["enormous",1],["sceptre",1],["renovated",1],["urge",1],["earth's",1],["crowns",1],["baubles",1],["abraham's",1],["enclosing",1],["dethroned",1],["heart's",1],["heaven's",1],["gifts",1],["giver",1],["fuel",1],["shade",1],["thirdly",1],["cleanse",1],["reconcile",1],["ransomed",1],["priesthood",1],["liken",1],["founded",1],["likened",1],["sunburnt",1],["reluctantly",1],["forbearing",1],["justly",1],["companionship",1],["ignored",1],["cockney",1],["villa",1],["swinging",1],["ward",1],["parole",1],["commit",1],["warder",1],["connive",1],["captive's",1],["locality",1],["designate",1],["combining",1],["lestranges",1],["reviving",1],["pastors",1],["gained",1],["qualities",1],["unsubstantial",1],["tinsel",1],["counterpart",1],["waste",1],["teaches",1],["savages",1],["polished",1],["gentlemen",1],["dogs",1],["delighting",1],["torment",1],["unfortunate",1],["unfledged",1],["sparrows",1],["taming",1],["urchins",1],["grand",1],["reference",1],["hands'",1],["dirty",1],["roughs'",1],["parasol",1],["design",1],["countenanced",1],["bonar's",1],["bonar",1],["lovingly",1],["appropriated",1],["hive",1],["alighted",1],["wail",1],["tapping",1],["industry",1],["occupants",1],["rocked",1],["haggard",1],["sleepless",1],["bore",1],["vainly",1],["wasted",1],["continuing",1],["poorly",1],["infant",1],["apologetically",1],["neglecting",1],["inside",1],["rocking",1],["consult",1],["lightened",1],["emptiness",1],["creep",1],["trained",1],["demands",1],["joyless",1],["arising",1],["monotony",1],["wayward",1],["fretfulness",1],["betray",1],["furrow",1],["serving",1],["attractive",1],["lambs",1],["mankind",1],["applaud",1],["acts",1],["munificence",1],["costly",1],["solomon",1],["sacrifices",1],["accepts",1],["obscurity",1],["keble",1],["trivial",1],["tripped",1],["embosomed",1],["tiny",1],["attic",1],["rattled",1],["ungainly",1],["figure",1],["merrily",1],["dainties",1],["buttered",1],["muffins",1],["toast",1],["cresses",1],["washerwoman",1],["decked",1],["homely",1],["bunches",1],["cowslips",1],["daffodils",1],["relaxed",1],["describing",1],["petty",1],["blunders",1],["recital",1],["crockery",1],["tendency",1],["mistresses",1],["loyal",1],["allegiance",1],["overleaped",1],["tyranny",1],["wooing",1],["conjugal",1],["circlet",1],["bony",1],["finger",1],["proved",1],["pole",1],["humming",1],["unprecedented",1],["wildwast",1],["straggling",1],["legible",1],["postmaster",1],["correspondent",1],["register",1],["scrawled",1],["wedded",1],["mayn't",1],["mayn",1],["enclosure",1],["inmost",1],["recesses",1],["scrawl",1],["ancor",1],["sutamton",1],["landed",1],["vry",1],["det",1],["pais",1],["punds",1],["afor",1],["thusday",1],["gret",1],["trubel",1],["abuit",1],["mister",1],["erdly",1],["id",1],["scrape",1],["mony",1],["hop",1],["beter",1],["fum",1],["yur",1],["scantily",1],["pawned",1],["fifth",1],["alooking",1],["forbids",1],["earns",1],["quarter's",1],["significant",1],["snatched",1],["shouted",1],["quickened",1],["movements",1],["random",1],["observations",1],["conflicting",1],["bone",1],["pound",1],["boots",1],["barefoot",1],["rent",1],["artful",1],["thorn",1],["humoured",1],["sorrowfully",1],["days'",1],["tidied",1],["recurring",1],["thursday",1],["vapour",1],["beg",1],["refuses",1],["candles",1],["hunger",1],["needn't",1],["needn",1],["duster",1],["broom",1],["accompanied",1],["test",1],["patriot",1],["swell",1],["delivering",1],["chieftain",1],["dripping",1],["bowlful",1],["beseech",1],["reversal",1],["reject",1],["messiah",1],["reversed",1],["rests",1],["hasten",1],["pierced",1],["conversion",1],["jew",1],["exclaims",1],["confidently",1],["await",1],["vaunt",1],["gilead",1],["deut",1],["omitted",1],["startling",1],["falter",1],["snow",1],["thirds",1],["harnessed",1],["bows",1],["rocks",1],["rang",1],["shouts",1],["conquering",1],["plough",1],["dwindled",1],["encamped",1],["judged",1],["whomsoever",1],["readeth",1],["sultry",1],["clime",1],["stooping",1],["cooling",1],["draught",1],["fame",1],["successes",1],["conspicuously",1],["excluded",1],["privilege",1],["brunt",1],["renown",1],["zealous",1],["dispensation",1],["finds",1],["strife",1],["assigns",1],["humbling",1],["purposely",1],["pertain",1],["illiterate",1],["shameful",1],["leaned",1],["reed",1],["loses",1],["liberal",1],["resources",1],["dwindle",1],["trustfully",1],["cruse",1],["surer",1],["granaries",1],["wealthy",1],["fade",1],["strewed",1],["advantages",1],["stripped",1],["lament",1],["losses",1],["fruitful",1],["labourers",1],["congregation",1],["dispersed",1],["concern",1],["ordained",1],["arthur's",1],["youngest",1],["steamer",1],["arrive",1],["hopeful",1],["nine",1],["boast",1],["background",1],["allowed",1],["benefactors",1],["communicated",1],["bleeding",1],["anxieties",1],["tied",1],["inattentive",1],["unpunctual",1],["chiding",1],["lain",1],["clatter",1],["pitying",1],["mantel",1],["belonging",1],["imperfect",1],["elegant",1],["heavier",1],["spoiled",1],["cranny",1],["crept",1],["unlikely",1],["pull",1],["exerting",1],["stuck",1],["jammed",1],["imperceptible",1],["breadth",1],["accident",1],["peered",1],["descent",1],["caution",1],["cellars",1],["recess",1],["slipped",1],["stains",1],["gleamed",1],["picked",1],["ajar",1],["resist",1],["shelves",1],["inherited",1],["candlesticks",1],["salvers",1],["tureens",1],["coins",1],["tarnished",1],["loosened",1],["indiscreet",1],["deadly",1],["impious",1],["abstain",1],["rescue",1],["confronted",1],["rivetted",1],["withdraw",1],["shrunken",1],["exercised",1],["fascination",1],["attributed",1],["serpent's",1],["serpent",1],["thieves",1],["partially",1],["originating",1],["sums",1],["unguarded",1],["burglar",1],["constructed",1],["revolved",1],["preventing",1],["fearfully",1],["hollow",1],["checked",1],["discreet",1],["aghast",1],["summary",1],["exact",1],["unloosed",1],["blanched",1],["threat",1],["strictest",1],["transpired",1],["beamed",1],["gushed",1],["comb",1],["stifled",1],["communicating",1],["crisp",1],["begun",1],["dews",1],["fern",1],["riser",1],["mounting",1],["wing",1],["pouring",1],["complication",1],["fasting",1],["shower",1],["astir",1],["tradesmen's",1],["tradesmen",1],["milkmaid",1],["pails",1],["ceased",1],["gleaming",1],["steep",1],["fatigue",1],["holding",1],["scarce",1],["landlord",1],["borrowing",1],["begging",1],["scraping",1],["inquisitive",1],["unaccountably",1],["informing",1],["unsuspicious",1],["wishing",1],["shrewd",1],["eh",1],["peering",1],["sort",1],["desperately",1],["flare",1],["akimbo",1],["ominously",1],["behave",1],["schooling",1],["unheard",1],["slamming",1],["offended",1],["abner's",1],["clumping",1],["appropriateness",1],["superseded",1],["worrit",1],["pegs",1],["anon",1],["youth's",1],["you're",1],["creases",1],["courtesied",1],["twitching",1],["collected",1],["valuable",1],["big",1],["daylight",1],["answering",1],["overlook",1],["duellist",1],["ordeal",1],["influenced",1],["conscientious",1],["respect",1],["tenderest",1],["filial",1],["disappoint",1],["pastoral",1],["uncounted",1],["henceforth",1],["plying",1],["torture",1],["appealing",1],["exhorting",1],["reproving",1],["inexplicable",1],["worst",1],["incur",1],["backed",1],["fastened",1],["baited",1],["wearied",1],["temples",1],["imagining",1],["corresponded",1],["earlier",1],["accounting",1],["vagaries",1],["spoons",1],["withstand",1],["educated",1],["basely",1],["succumbed",1],["avowing",1],["considering",1],["insignificant",1],["cipher",1],["members",1],["discarded",1],["faulty",1],["immortals",1],["warmth",1],["behalf",1],["clue",1],["allusion",1],["careful",1],["thistle",1],["runaway",1],["scourges",1],["feathers",1],["courteously",1],["declining",1],["blended",1],["overlooked",1],["tapped",1],["attitude",1],["trickled",1],["tugged",1],["button",1],["jacket",1],["nostrils",1],["jerked",1],["shuffled",1],["choking",1],["disingenuous",1],["conclusions",1],["straightforward",1],["guile",1],["apologize",1],["repetition",1],["clutched",1],["meantime",1],["unjustly",1],["accused",1],["visitors",1],["smoothing",1],["apron",1],["tucked",1],["sleeves",1],["ushered",1],["adherence",1],["answerable",1],["doings",1],["embarrassment",1],["fruitless",1],["extended",1],["confirming",1],["testimony",1],["clattering",1],["partake",1],["hospitality",1],["foreign",1],["unrefreshed",1],["member",1],["imputation",1],["calumny",1],["they're",1],["lad's",1],["mass",1],["shaggy",1],["bat",1],["maule",1],["goin'",1],["jail",1],["begged",1],["drawled",1],["madness",1],["descends",1],["rag",1],["handkerchief",1],["bruised",1],["swollen",1],["hurt",1],["moaned",1],["disobey",1],["steady's",1],["championship",1],["attacks",1],["duration",1],["clock",1],["covetous",1],["lets",1],["comforts",1],["vexed",1],["deprive",1],["counted",1],["tis",1],["weaker",1],["nowhere",1],["raising",1],["ray",1],["glimmered",1],["ashamed",1],["accusers",1],["claiming",1],["rights",1],["folded",1],["toward",1],["taunts",1],["parents'",1],["thoroughly",1],["panes",1],["cleaned",1],["neatness",1],["mending",1],["darn",1],["patch",1],["skill",1],["event",1],["deferred",1],["kneel",1],["worshipper",1],["mindful",1],["remembereth",1],["permit",1],["removeth",1],["prop",1],["reduced",1],["resolute",1],["victims",1],["conquest",1],["circumstance",1],["phurah",1],["afterward",1],["adventure",1],["attendant",1],["treading",1],["spreads",1],["amalek",1],["innumerable",1],["slumbering",1],["grasshoppers",1],["camels",1],["tethered",1],["approaches",1],["dreamed",1],["guessing",1],["cake",1],["barley",1],["tumbled",1],["smote",1],["overturned",1],["renewed",1],["encouragements",1],["wonders",1],["mutiny",1],["suggests",1],["gun",1],["encompassed",1],["captors",1],["guessed",1],["scrap",1],["torn",1],["comforteth",1],["shouldest",1],["grass",1],["forgettest",1],["maker",1],["heavens",1],["continually",1],["exile",1],["hasteneth",1],["li",1],["englishwomen",1],["midianite's",1],["rearing",1],["aloft",1],["lean",1],["fullest",1],["defiled",1],["wanderer",1],["beam",1],["meets",1],["blesses",1],["campaign",1],["forsake",1],["established",1],["multiply",1],["instances",1],["records",1],["assail",1],["endureth",1],["songs",1],["believer",1],["ripens",1],["swells",1],["growth",1],["extend",1],["thinketh",1],["proposing",1],["thrust",1],["epistle",1],["tinted",1],["document",1],["destination",1],["per",1],["cent",1],["appoint",1],["acquainted",1],["carries",1],["truthfulness",1],["sceptical",1],["clash",1],["fastest",1],["sailer",1],["depending",1],["client",1],["intending",1],["apprise",1],["overwhelmed",1],["craft",1],["embarked",1],["scrupulous",1],["enormity",1],["root",1],["absorbing",1],["cunning",1],["cleverness",1],["foolishness",1],["unlawful",1],["rightfully",1],["belonged",1],["consequence",1],["debased",1],["subdue",1],["oozed",1],["ruin",1],["phantoms",1],["quit",1],["intimacy",1],["friendship",1],["purer",1],["dawning",1],["beings",1],["impersonification",1],["bearer",1],["discord",1],["haughty",1],["stung",1],["scorpion",1],["accord",1],["consequences",1],["behaviour",1],["blush",1],["aside",1],["loosening",1],["braced",1],["commentary",1],["meekness",1],["harbour",1],["despise",1],["allied",1],["indecision",1],["confidante",1],["unconsciously",1],["issue",1],["lawsuit",1],["trenching",1],["compound",1],["restoration",1],["residue",1],["plans",1],["expedients",1],["concluding",1],["actively",1],["untouched",1],["nobler",1],["farthing",1],["gnawing",1],["possessing",1],["bloodless",1],["groan",1],["galled",1],["replying",1],["resumed",1],["vacillating",1],["pendulum",1],["perpetually",1],["snatches",1],["fog",1],["failed",1],["abstracted",1],["melodious",1],["fairer",1],["completing",1],["toilet",1],["minutes'",1],["partic'lar",1],["partic",1],["'lar",1],["roadside",1],["dignified",1],["coarse",1],["vulgar",1],["pitted",1],["writ",1],["tom",1],["jim",1],["sixpenny",1],["chay",1],["stables",1],["portal",1],["incoherent",1],["rattle",1],["lodgings",1],["they'll",1],["un",1],["michaelmas",1],["distracted",1],["vociferous",1],["emergency",1],["taylor's",1],["frighten",1],["customers",1],["deepest",1],["proposed",1],["minor",1],["exposing",1],["subjected",1],["brightest",1],["comfortless",1],["gemmed",1],["exquisite",1],["detain",1],["decide",1],["implore",1],["tangled",1],["discern",1],["perchance",1],["orders",1],["arrangements",1],["preparation",1],["shortness",1],["incapacity",1],["unwillingness",1],["elapsed",1],["chaise",1],["swathed",1],["blankets",1],["drag",1],["tottering",1],["feebly",1],["prospects",1],["strongest",1],["proofs",1],["constraineth",1],["samaritan",1],["noon",1],["pronounced",1],["prescribed",1],["forbade",1],["enforce",1],["assist",1],["volunteered",1],["obtained",1],["relate",1],["dearer",1],["romance",1],["vital",1],["parishioner",1],["uncommon",1],["shot",1],["bramley",1],["bend",1],["inquire",1],["undertaker",1],["homeward",1],["loath",1],["fragrant",1],["priceless",1],["jewel",1],["yon",1],["unselfish",1],["partner",1],["guardian",1],["fascinated",1],["flattered",1],["resolve",1],["helper",1],["hinderer",1],["activity",1],["shun",1],["perch",1],["secluded",1],["beauteous",1],["aspire",1],["loveliness",1],["divide",1],["valued",1],["link",1],["bind",1],["catches",1],["plodded",1],["highroad",1],["nursed",1],["flames",1],["whirled",1],["exclaiming",1],["emaciated",1],["recover",1],["medical",1],["strictly",1],["recognition",1],["quarters",1],["alarming",1],["voyage",1],["pupils",1],["remonstrance",1],["gaily",1],["objection",1],["tire",1],["greetings",1],["begins",1],["inconvenient",1],["laboured",1],["tonic",1],["enfeebled",1],["constitution",1],["landmarks",1],["fortunes",1],["cure",1],["shortest",1],["teetotaller",1],["declaim",1],["evils",1],["rallied",1],["wonderfully",1],["uncharitable",1],["subjects",1],["censure",1],["fares",1],["methinks",1],["mind's",1],["reciprocated",1],["weighing",1],["grin",1],["plodding",1],["vehicle",1],["exhilarating",1],["literally",1],["onwards",1],["squirrel",1],["encountering",1],["throng",1],["conveying",1],["contemplate",1],["triumphs",1],["prefigured",1],["bow",1],["wolves",1],["armour",1],["companies",1],["brake",1],["pitchers",1],["slumbers",1],["blare",1],["waving",1],["lit",1],["bursts",1],["strikes",1],["panic",1],["confused",1],["distinguish",1],["snatch",1],["vigour",1],["instinct",1],["possesses",1],["vast",1],["speed",1],["careless",1],["trampling",1],["corpses",1],["brothers",1],["forlorn",1],["despatched",1],["seize",1],["intercept",1],["foreshadowed",1],["wickedness",1],["shrouded",1],["moral",1],["rome",1],["towered",1],["supreme",1],["subjection",1],["shrines",1],["myriads",1],["overthrow",1],["altars",1],["unlearned",1],["engage",1],["mohammed",1],["symbol",1],["incarnate",1],["resoundeth",1],["examples",1],["shining",1],["dispelling",1],["glorify",1],["martyrs",1],["exception",1],["banished",1],["lights",1],["enlightening",1],["torch",1],["rehearsal",1],["infinitely",1],["consciences",1],["degrade",1],["enslave",1],["resolutions",1],["virtue",1],["assault",1],["emblems",1],["distinct",1],["dispensations",1],["shattering",1],["puts",1],["destroyer",1],["aim",1],["patriarch",1],["severest",1],["conflicts",1],["enlisted",1],["isaac",1],["dashing",1],["dashed",1],["obscured",1],["ripe",1],["shone",1],["richness",1],["graces",1],["ripen",1],["crudeness",1],["developed",1],["softness",1],["yields",1],["planted",1],["rivers",1],["prosper",1],["travellers",1],["satire",1],["remonstrances",1],["nurses",1],["dressing",1],["motionless",1],["mutely",1],["transfixing",1],["gorgon",1],["magnified",1],["efface",1],["marks",1],["sponge",1],["interested",1],["lavishes",1],["attentions",1],["hypocritical",1],["penetrate",1],["designs",1],["politeness",1],["sarcastic",1],["cheers",1],["blending",1],["shriller",1],["huzzas",1],["villagers",1],["concealing",1],["muslin",1],["population",1],["forgetful",1],["envy",1],["instructing",1],["hers",1],["sown",1],["upright",1],["prized",1],["inscribed",1],["tormented",1],["seduce",1],["tempters",1],["masters",1],["tyrants",1],["galling",1],["acutely",1],["degradation",1],["thawing",1],["ungenial",1],["undefined",1],["leaning",1],["vivid",1],["denoted",1],["languid",1],["honourable",1],["agitated",1],["bids",1],["directs",1],["restitution",1],["strode",1],["presently",1],["acknowledge",1],["reproachfully",1],["spectre",1],["veins",1],["foreboding",1],["thickened",1],["disease",1],["looming",1],["childlike",1],["outweighed",1],["unreservedly",1],["withhold",1],["ripened",1],["mellowed",1],["peach",1],["surface",1],["thunder",1],["trickle",1],["harmlessly",1],["agony",1],["irresolution",1],["injury",1],["premises",1],["europe",1],["antecedents",1],["avenging",1],["prognostications",1],["dreams",1],["toll",1],["funeral",1],["plumes",1],["hearse",1],["nodding",1],["pall",1],["disordered",1],["shadows",1],["ceiling",1],["shapes",1],["appalled",1],["portrait",1],["mantelpiece",1],["threatening",1],["hark",1],["bars",1],["stealthy",1],["footstep",1],["creaking",1],["robbers",1],["uncertainty",1],["couch",1],["moaning",1],["palsied",1],["definite",1],["floating",1],["ascertaining",1],["packed",1],["accidental",1],["nourishment",1],["deathly",1],["overthrew",1],["clinking",1],["regain",1],["posture",1],["numbness",1],["suspended",1],["senseless",1],["besprinkled",1],["exist",1],["catalepsy",1],["enchained",1],["faculties",1],["muscle",1],["jealously",1],["edifice",1],["crumbled",1],["dug",1],["nameless",1],["skeleton",1],["heaps",1],["meditated",1],["arrested",1],["flickered",1],["socket",1],["enslaved",1],["cankered",1],["rust",1],["eat",1],["heaped",1],["penned",1],["hopefully",1],["factory",1],["glowed",1],["opposite",1],["gleam",1],["western",1],["horizon",1],["ruddy",1],["faded",1],["hue",1],["corner",1],["lifting",1],["how's",1],["convulsive",1],["sobs",1],["penitent",1],["regained",1],["composure",1],["penitence",1],["quenched",1],["hour's",1],["uninterrupted",1],["noised",1],["impelled",1],["tormenting",1],["weeping",1],["meant",1],["attempts",1],["faltering",1],["noisy",1],["reeling",1],["ale",1],["stolid",1],["outburst",1],["buoyed",1],["amen",1],["omission",1],["vividly",1],["mourner",1],["blank",1],["faithfully",1],["palestine",1],["diverted",1],["gossips",1],["widely",1],["slander",1],["gentlefolk",1],["anyways",1],["retail",1],["draper's",1],["draper",1],["unceremoniously",1],["seating",1],["darkened",1],["bewitched",1],["what's",1],["wildwaste's",1],["commotion",1],["oath",1],["searched",1],["dan",1],["gloomily",1],["bog's",1],["ride",1],["disappearing",1],["notion",1],["on't",1],["lunnon",1],["hat",1],["hanging",1],["odder",1],["madman",1],["disorder",1],["stifle",1],["impatiently",1],["peg",1],["entreaty",1],["daughter's",1],["urgent",1],["drawing",1],["opposing",1],["insisting",1],["hastening",1],["dismal",1],["starved",1],["slackened",1],["pace",1],["images",1],["shades",1],["halfpenny",1],["moist",1],["wider",1],["admittance",1],["cleaning",1],["fetching",1],["upside",1],["pump",1],["wash",1],["ringing",1],["seized",1],["darted",1],["owing",1],["causing",1],["grope",1],["push",1],["resisting",1],["obstruction",1],["prevented",1],["shriek",1],["clammy",1],["they've",1],["agonized",1],["rounds",1],["obscure",1],["terrified",1],["gasped",1],["piercing",1],["imprisonment",1],["paralyzed",1],["unutterable",1],["loudly",1],["reveal",1],["murder",1],["uppermost",1],["summon",1],["men's",1],["unwounded",1],["unhurt",1],["acquiring",1],["thanked",1],["judgments",1],["harden",1],["thunderbolt",1],["shatter",1],["dives",1],["reprieve",1],["lurid",1],["worthlessness",1],["immortal",1],["besought",1],["knife",1],["surgeon",1],["milder",1],["acknowledging",1],["counselled",1],["administered",1],["opiate",1],["felix",1],["hated",1],["stupor",1],["quickening",1],["lethargic",1],["lure",1],["destruction",1],["zaccheus",1],["irresolute",1],["intrusted",1],["responsible",1],["reascended",1],["insuperable",1],["consented",1],["tend",1],["elevated",1],["enjoying",1],["noblest",1],["repaying",1],["respected",1],["representative",1],["confess",1],["supporting",1],["banister",1],["fibre",1],["outskirts",1],["burdened",1],["imbibed",1],["adopted",1],["namely",1],["persisted",1],["governed",1],["robert",1],["walpole",1],["cash",1],["fed",1],["inconsistency",1],["confirm",1],["theory",1],["mask",1],["fallacy",1],["justify",1],["level",1],["admitted",1],["infectious",1],["ice",1],["encrusted",1],["grittons",1],["acting",1],["frigid",1],["scepticism",1],["disappearance",1],["flies",1],["insolence",1],["sneering",1],["remark",1],["capable",1],["cherish",1],["disinterested",1],["proffered",1],["quarrelled",1],["exploring",1],["realizing",1],["experiencing",1],["salutary",1],["upper",1],["disturbance",1],["hurrying",1],["tending",1],["thirst",1],["hoping",1],["binding",1],["fiction",1],["margin",1],["cushioned",1],["desultory",1],["dost",1],["hymn",1],["especial",1],["perused",1],["seclusion",1],["introduced",1],["enthrone",1],["thyself",1],["reign",1],["rival",1],["playing",1],["accomplice",1],["spite",1],["requiring",1],["integrity",1],["expedient",1],["confine",1],["sentimental",1],["closet",1],["noiselessly",1],["sensations",1],["reaction",1],["delirious",1],["bracing",1],["fluttered",1],["articulating",1],["believes",1],["court",1],["throbbing",1],["convict",1],["tribunal",1],["compensation",1],["suffice",1],["throws",1],["amply",1],["burying",1],["oblivion",1],["fervour",1],["tenfold",1],["malignant",1],["uprightness",1],["sermons",1],["exemplified",1],["humiliated",1],["tribute",1],["acknowledgment",1],["inferiority",1],["occurrences",1],["rumours",1],["reinstated",1],["changing",1],["besieged",1],["inquirers",1],["smiled",1],["exaggerations",1],["pebble",1],["liberally",1],["placid",1],["equipped",1],["pair",1],["loaded",1],["revolvers",1],["crowds",1],["thronged",1],["curiously",1],["bullion",1],["buy",1],["sturdy",1],["barrels",1],["insidious",1],["enrich",1],["achan",1],["heapeth",1],["unrighteously",1],["encountered",1],["fugitives",1],["secondary",1],["calledst",1],["wentest",1],["jealous",1],["chafed",1],["gleaning",1],["grapes",1],["vintage",1],["adds",1],["abated",1],["completed",1],["failing",1],["craved",1],["supplies",1],["inhospitable",1],["missionaries",1],["error",1],["loaves",1],["fighting",1],["verily",1],["lack",1],["hardens",1],["closes",1],["refuse",1],["inasmuch",1],["cursed",1],["track",1],["karkor",1],["warfare",1],["presses",1],["sheathe",1],["unsubdued",1],["relax",1],["inherit",1],["discourage",1],["doomed",1],["races",1],["investigation",1],["prompt",1],["kin",1],["commandment",1],["revenger",1],["meeteth",1],["num",1],["xxxv",1],["alluding",1],["violence",1],["liveth",1],["born",1],["conqueror",1],["fate",1],["crimes",1],["deserved",1],["enthusiastic",1],["freed",1],["dynasty",1],["rulers",1],["belongeth",1],["ripening",1],["glorified",1],["perils",1],["exploits",1],["likeness",1],["angel's",1],["poet",1],["whate'er",1],["whate",1],["'er",1],["tear",1],["invaded",1],["metaphor",1],["verdure",1],["vineyard",1],["cumbereth",1],["profession",1],["beareth",1],["overcometh",1],["fulness",1],["evermore",1],["realm",1],["everlasting",1],["incidents",1],["personages",1],["overlooks",1],["clad",1],["drapery",1],["spangled",1],["bathing",1],["magnificent",1],["orb",1],["upwards",1],["streams",1],["islands",1],["float",1],["ether",1],["finer",1],["mortals",1],["glories",1],["resplendent",1],["bridal",1],["owes",1],["radiance",1],["glistened",1],["fount",1],["finished",1],["triumphal",1],["arch",1],["evergreens",1],["roses",1],["daybreak",1],["garland",1],["illumination",1],["enthusiasm",1],["gayly",1],["wedding",1],["succeed",1],["drunkenness",1],["riot",1],["blot",1],["shift",1],["crutches",1],["welcomes",1],["widowed",1],["grieved",1],["inexpressibly",1],["traces",1],["asperity",1],["harshly",1],["braving",1],["dis",1],["guarded",1],["exceeding",1],["withering",1],["vision",1],["sweeten",1],["willed",1],["retains",1],["dawns",1],["hebrew",1],["practice",1],["killer",1],["nocross",1],["famous",1],["physician",1],["provence",1],["cyril",1],["ashley",1],["claudia",1],["pilgrims",1],["museum",1],["robbers'",1],["cabul",1],["roby",1],["flora",1],["rambles",1],["rat",1],["whispering",1],["unseen",1],["furnish",1],["shoes",1],["zaida's",1],["zaida",1],["mothers",1],["shilling",1],["sixteen",1],["travels",1],["beautifully",1],["recent",1],["topographical",1],["foulquier",1],["handsomely",1],["distinguished",1],["vivacity",1],["lucidity",1],["eminently",1],["pretend",1],["sketch",1],["delineate",1],["landscapes",1],["cull",1],["choicest",1],["episodes",1],["spanish",1],["unfailing",1],["discrimination",1],["felicity",1],["kane's",1],["kane",1],["arctic",1],["explorations",1],["grinnel",1],["franklin",1],["sixty",1],["woodcuts",1],["extra",1],["missionary",1],["lands",1],["authors",1],["luther",1],["enlarged",1],["maury's",1],["maury",1],["geography",1],["thirteen",1],["charts",1],["british",1],["india",1],["hugh",1],["murray",1],["esq",1],["r",1],["continuation",1],["collier's",1],["collier",1],["colonial",1],["empire",1],["scotland",1],["james",1],["mackenzie",1],["pictures",1],["sicily",1],["bartlett",1],["revised",1],["delineation",1],["islay",1],["burns",1],["glasgow",1],["notices",1],["localities",1],["sketches",1],["g",1],["blaikie",1],["maps",1],["updated",1],["renamed",1],["print",1],["rules",1],["reports",1],["performances",1],["modified",1],["file",1],["indicate",1],["accept",1],["cease",1],["pglaf",1],["compilation",1],["unprotected",1],["sharing",1],["govern",1],["countries",1],["downloading",1],["representations",1],["accessed",1],["texts",1],["indicating",1],["charges",1],["appearing",1],["imposed",1],["unlink",1],["detach",1],["files",1],["redistribute",1],["convert",1],["binary",1],["compressed",1],["nonproprietary",1],["proprietary",1],["processing",1],["hypertext",1],["version",1],["expense",1],["exporting",1],["alternate",1],["include",1],["viewing",1],["reasonable",1],["gross",1],["derive",1],["method",1],["calculate",1],["taxes",1],["owed",1],["agreed",1],["legally",1],["periodic",1],["notifies",1],["mail",1],["require",1],["discontinue",1],["reported",1],["group",1],["manager",1],["employees",1],["expend",1],["identify",1],["transcribe",1],["proofread",1],["despite",1],["defects",1],["incomplete",1],["inaccurate",1],["corrupt",1],["data",1],["transcription",1],["infringement",1],["damaged",1],["disk",1],["virus",1],["codes",1],["disclaim",1],["remedies",1],["negligence",1],["contract",1],["distributor",1],["liable",1],["indirect",1],["consequential",1],["punitive",1],["elect",1],["is'",1],["merchantability",1],["fitness",1],["disclaimers",1],["exclusion",1],["violates",1],["interpreted",1],["maximum",1],["invalidity",1],["unenforceability",1],["provision",1],["void",1],["remaining",1],["provisions",1],["indemnity",1],["indemnify",1],["employee",1],["production",1],["promotion",1],["harmless",1],["occur",1],["alteration",1],["modification",1],["additions",1],["deletions",1],["synonymous",1],["formats",1],["variety",1],["obsolete",1],["exists",1],["hundreds",1],["walks",1],["financial",1],["critical",1],["goals",1],["ensuring",1],["sections",1],["non",1],["educational",1],["corporation",1],["organized",1],["mississippi",1],["internal",1],["revenue",1],["ein",1],["identification",1],["deductible",1],["extent",1],["state's",1],["ut",1],["depends",1],["survive",1],["widespread",1],["licensed",1],["accessible",1],["array",1],["outdated",1],["maintaining",1],["irs",1],["regulating",1],["charities",1],["charitable",1],["uniform",1],["paperwork",1],["locations",1],["determine",1],["solicitation",1],["prohibition",1],["accepting",1],["unsolicited",1],["donors",1],["international",1],["gratefully",1],["statements",1],["treatment",1],["swamp",1],["donation",1],["methods",1],["checks",1],["card",1],["professor",1],["michael",1],["hart",1],["originator",1],["loose",1],["network",1],["volunteer",1],["necessarily",1],["main",1],["pg",1],["facility",1],["includes",1],["subscribe",1],["newsletter",1]],"tagger-version":"v2.3.0"}