{"id":68067,"title":"Frank Reade, Jr., with his new steam horse in the great American desert: or, The sandy trail of death","authors":[{"name":"Senarens, Luis","birth_year":1863,"death_year":1939}],"translators":[],"subjects":["Adventure stories","American fiction -- 19th century","Dime novels","Inventors -- United States -- Fiction","Popular literature -- United States","Science fiction","Western stories"],"bookshelves":[],"languages":["en"],"copyright":false,"media_type":"Text","formats":{"text/html":"https://www.gutenberg.org/ebooks/68067.html.images","application/zip":"https://www.gutenberg.org/files/68067/68067-0.zip","application/epub+zip":"https://www.gutenberg.org/ebooks/68067.epub.images","image/jpeg":"https://www.gutenberg.org/cache/epub/68067/pg68067.cover.small.jpg","application/rdf+xml":"https://www.gutenberg.org/ebooks/68067.rdf","text/plain":"https://www.gutenberg.org/ebooks/68067.txt.utf-8","application/x-mobipocket-ebook":"https://www.gutenberg.org/ebooks/68067.kindle.images","text/plain; charset=us-ascii":"https://www.gutenberg.org/files/68067/68067-0.txt"},"download_count":538}